Workbook
Name AsAt_Date: Assumptions!$D$13
Name Cat_ChargesVAT: Categories!$F$8:$F$18
Name Cat_Class: Categories!$D$8:$D$18
Name Cat_Codes: Categories!$B$8:$B$18
Name Cat_Direction: Categories!$E$8:$E$18
Name Cat_InputDeductible: Categories!$G$8:$G$18
Name Cat_Name: Categories!$C$8:$C$18
Name Cat_Rate: Categories!$M$8:$M$18
Name Cat_Recoverable: Categories!$N$8:$N$18
Name Combined_VAT_Rate: Assumptions!$D$25
Name COVID_Rate: Assumptions!$D$23
Name COVID_Rate_Prior: Assumptions!$D$24
Name Dir_In: Cash_Flow!$F$7
Name Dir_Out: Cash_Flow!$F$8
Name Dup_Exclusions: Error_Flags!$F$7:$H$7
Name GETFund_Rate: Assumptions!$D$22
Name Ledger_Year: Assumptions!$D$12
Name NHIL_Rate: Assumptions!$D$21
Name NoInv_Exempt: Error_Flags!$F$6
Name Opening_Cash: Cash_Flow!$F$6
Name Prefix_Inflow: Error_Flags!$F$9
Name Prefix_Outflow: Error_Flags!$F$10
Name Remit_Kw1: Cash_Flow!$F$10
Name Remit_Kw2: Cash_Flow!$G$10
Name Sim_End: Assumptions!$D$11
Name Sim_Start: Assumptions!$D$10
Name Suspect_Categories: Error_Flags!$F$11
Name Suspect_Keywords: Error_Flags!$F$12:$M$12
Name Tax_Authority: Cash_Flow!$F$9
Name Tax_Tolerance: Error_Flags!$F$8
Name VAT_Flat_Rate: Assumptions!$D$26
Name VAT_Rate: Assumptions!$D$20
Name VAT_Threshold_Goods: Assumptions!$D$27
Name VAT_Threshold_Services: Assumptions!$D$28
Name VAT_WHT_Rate: Assumptions!$D$29
Name VR_Output_Tax_Total: VAT_Recon!$C$17+VAT_Recon!$D$17+VAT_Recon!$E$17
Name VR_Withheld_At_Source: VAT_Recon!$G$30
Name WHT_Goods: Assumptions!$D$30
Name WHT_Services: Assumptions!$D$31
Name WHT_Threshold: Assumptions!$D$33
Name WHT_Works: Assumptions!$D$32

Sheet Assumptions
B1: NKABOM HAULAGE LTD — CORE TAX ENGINE
B2: Sheet 1 of 6 • Assumptions & Controlled Tax Parameters • Petroleum Products Haulage, Ghana
B3: SIMULATION ONLY — All entity, counterparty, invoice and transaction data in this workbook is fictitious. This workbook is a control and reporting tool, not tax advice. Confirm all rates with the Ghana Revenue Authority before filing.
B5: A. ENTITY & SIMULATION CONTROL PANEL
B6: Parameter | D6: Entry | H6: Notes
B7: Entity name | D7: Nkabom Haulage Ltd | H7: Simulated taxpayer. Not a real registered company.
B8: Business activity | D8: Petroleum products haulage | H8: Bulk fuel cartage for OMCs and BDCs; ancillary logistics services.
B9: Reporting currency | D9: GHS | H9: Ghana Cedi. All amounts in this workbook are stated in GHS.
B10: Simulation period — start | D10: 46023 | H10: Period chosen so that the rates in force under the VAT Act, 2025 (Act 1151) apply throughout.
B11: Simulation period — end | D11: 46387 | H11: Twelve monthly VAT periods, supporting monthly reconciliation and cash-flow reporting.
B12: Ledger year | D12: 2026 | H12: Calendar year the Ledger transactions fall in. Driven centrally — the Ledger reads this as Ledger_Year.
B13: Assumptions "As at" date | D13: 46286 | H13: Date the rates and thresholds below were last verified against primary sources.
B14: VAT registration status | D14: Registered | H14: Assumed registered and standard-rated; turnover exceeds the registration threshold in B.7.
B15: VAT withholding agent? | D15: No | H15: The company is not an appointed agent, but suffers VAT withholding on some customer receipts.
B16: Prepared by / Reviewed by | D16: Finance — Tax | H16: Update on each review cycle. Rates should be re-verified at least quarterly.
B18: B. CONTROLLED TAX RATES & THRESHOLDS — these are the ONLY places a rate should ever be changed
B19: Parameter Code | C19: Parameter | D19: Value | E19: Unit | F19: Effective From | G19: Effective To | H19: Description / How it is used in this workbook | I19: Source Document (primary) | J19: Section / Provision | K19: Source Type | L19: Source Reference
B20: VAT_Rate | C20: Value Added Tax — standard rate | D20: 0.15 | E20: % of taxable value | F20: 46023 | G20: Open | H20: Core VAT rate. Applied to the net (tax-exclusive) amount of standard-rated supplies made and received. | I20: Value Added Tax Act, 2025 (Act 1151), as explained in GRA guidance on the 2026 VAT reforms | J20: s.3 — imposition of VAT at the standard rate; GRA VAT tax-type guidance | K20: Statute + GRA | L20: https://gra.gov.gh/domestic-tax/tax-types/vat/
B21: NHIL_Rate | C21: National Health Insurance Levy (NHIL) | D21: 0.025 | E21: % of taxable value | F21: 46023 | G21: Open | H21: Charged on the same base as VAT. Recoverable as input tax from 1 Jan 2026 following re-coupling. | I21: National Health Insurance Act, 2012 (Act 852), as amended by the National Health Insurance (Amendment) Act, 2025 — source for input tax deductibility; base re-coupled to VAT by the Value Added Tax Act, 2025 (Act 1151) | J21: National Health Insurance (Amendment) Act, 2025, number to confirm — re-coupling of the levy to the VAT base and input tax deductibility; GRA 2026 VAT reform guidance — Confirm section in Act text | K21: Statute + GRA | L21: https://gra.gov.gh/domestic-tax/tax-types/vat/
B22: GETFund_Rate | C22: Ghana Education Trust Fund Levy (GETFund) | D22: 0.025 | E22: % of taxable value | F22: 46023 | G22: Open | H22: Charged on the same base as VAT. Recoverable as input tax from 1 Jan 2026 following re-coupling. | I22: Ghana Education Trust Fund (Amendment) Act, 2018 (Act 972), as further amended by the Ghana Education Trust Fund (Amendment) Act, 2025 — source for input tax deductibility; base re-coupled to VAT by the Value Added Tax Act, 2025 (Act 1151) | J22: Ghana Education Trust Fund (Amendment) Act, year and number to confirm — re-coupling of the levy to the VAT base and input tax deductibility; GRA 2026 VAT reform guidance — Confirm section in Act text | K22: Statute + GRA | L22: https://gra.gov.gh/domestic-tax/tax-types/vat/
B23: COVID_Rate | C23: COVID-19 Health Recovery Levy — current | D23: 0 | E23: % of taxable value | F23: 46023 | G23: Open | H23: ABOLISHED. Held at 0% so the levy stays visible in the engine and can be reinstated centrally if ever re-enacted. | I23: COVID-19 Health Recovery Levy Repeal Act, 2025 — abolishes the levy created by the COVID-19 Health Recovery Levy Act, 2021 (Act 1068) | J23: Repeal of the COVID-19 Health Recovery Levy Act, 2021 (Act 1068); GRA VAT tax-type guidance on the 2026 reforms | K23: Statute + GRA | L23: https://gra.gov.gh/domestic-tax/tax-types/vat/
B24: COVID_Rate_Prior | C24: COVID-19 Health Recovery Levy — superseded | D24: 0.01 | E24: % of taxable value | F24: 44317 | G24: 46022 | H24: HISTORIC ONLY — not used by any calculation. Retained to document the basis for periods before 1 Jan 2026. | I24: COVID-19 Health Recovery Levy Act, 2021 (Act 1068) | J24: Act 1068 (imposition of the 1% levy), in force to 31 December 2025 | K24: Statute + GRA | L24: https://gra.gov.gh/domestic-tax/tax-types/vat/
B25: Combined_VAT_Rate | C25: Combined effective VAT & levy rate | D25: =D20+D21+D22+D23 -> 0.2 | E25: % of taxable value | F25: =F20 -> 46023 | G25: Open | H25: DERIVED — do not overtype. VAT, NHIL and GETFund now sit on the same base, so the three simply add to 20%. This is the single rate the Ledger applies to standard-rated lines. | I25: Derived from VAT_Rate + NHIL_Rate + GETFund_Rate + COVID_Rate above | J25: Confirmed by GRA: the levies are charged on the same base as VAT (no cascading) | K25: Derived | L25: https://gra.gov.gh/domestic-tax/tax-types/vat/
B26: VAT_Flat_Rate | C26: VAT Flat Rate Scheme (VFRS) | D26: Abolished | E26: n/a — scheme withdrawn | F26: 46023 | G26: Open | H26: 3% and 5% flat rate regimes ended by Act 1151. All eligible suppliers use the 15% standard rate. | I26: Value Added Tax Act, 2025 (Act 1151) | J26: Abolition of the VAT Flat Rate Scheme; 3% on goods and 5% on immovable property withdrawn | K26: Statute + GRA | L26: https://gra.gov.gh/news/portfolio/notice-to-all-vat-registered-taxpayers/
B27: VAT_Threshold_Goods | C27: VAT registration threshold — goods | D27: 750000 | E27: GHS per annum | F27: 46023 | G27: Open | H27: Turnover level above which registration is compulsory for a goods business. Raised from GHS 200,000 by Act 1151. | I27: Value Added Tax Act, 2025 (Act 1151) | J27: Registration threshold — supply of goods | K27: GRA | L27: https://gra.gov.gh/news/portfolio/notice-to-all-vat-registered-taxpayers/
B28: VAT_Threshold_Services | C28: VAT registration threshold — services | D28: None | E28: Register within 30 days of starting taxable services | F28: 46023 | G28: Open | H28: No turnover test applies to this company. It registers regardless of turnover, on commencing taxable services, and accounts for VAT on all standard-rated supplies from day one. | I28: Value Added Tax Act, 2025 (Act 1151); GRA VAT tax-type guidance | J28: Registration obligation — supply of services; registration on commencement rather than by turnover | K28: Statute + GRA | L28: https://gra.gov.gh/news/portfolio/notice-to-all-vat-registered-taxpayers/
B29: VAT_WHT_Rate | C29: VAT withholding rate (appointed agents) | D29: 0.07 | E29: % of taxable value | F29: 46023 | G29: Open | H29: Withheld by appointed customers from amounts due to the company. A payment credit, not an extra tax — it does not change output VAT. Applies only when an appointed VAT withholding agent pays a VAT-registered supplier. Base is the tax-exclusive value. | I29: Ghana Revenue Authority — VAT Withholding guidance; Value Added Tax Act, 2025 (Act 1151) | J29: Act 1151 s.56, withholding of 7% of taxable output value. s.55, appointment of agents, confirm in Act text. | K29: GRA | L29: https://gra.gov.gh/domestic-tax/tax-types/vat-withholding/
B30: WHT_Goods | C30: Withholding tax — supply of goods (resident) | D30: 0.03 | E30: % of payment | F30: Not changed by Act 1151 | G30: Open | H30: Income-tax withholding on payments to resident suppliers of goods. Separate from VAT — kept here so the Ledger can reference it centrally. | I30: Income Tax Act, 2015 (Act 896), as amended | J30: First Schedule, paragraph 8 — withholding on supply of goods | K30: Statute | L30: https://gra.gov.gh/domestic-tax/tax-types/withholding-tax/
B31: WHT_Services | C31: Withholding tax — supply of services (resident) | D31: 0.075 | E31: % of payment | F31: Not changed by Act 1151 | G31: Open | H31: The rate most relevant to this company: haulage is a service, so customers who are withholding agents deduct 7.5% from fees. | I31: Income Tax Act, 2015 (Act 896), as amended | J31: First Schedule, paragraph 8 — withholding on service fees | K31: Statute | L31: https://gra.gov.gh/domestic-tax/tax-types/withholding-tax/
B32: WHT_Works | C32: Withholding tax — works (resident) | D32: 0.05 | E32: % of payment | F32: Not changed by Act 1151 | G32: Open | H32: Applies to works contracts, e.g. depot civil works. Included for completeness of the withholding category. | I32: Income Tax Act, 2015 (Act 896), as amended | J32: First Schedule, paragraph 8 — withholding on works | K32: Statute | L32: https://gra.gov.gh/domestic-tax/tax-types/withholding-tax/
B33: WHT_Threshold | C33: Withholding tax threshold (goods/works/services) | D33: 2000 | E33: GHS per annum cumulative per payee | F33: Not changed by Act 1151 | G33: Open | H33: Cumulative annual payments to one person below this level are not subject to withholding. Not a VAT threshold — do not confuse with VAT_Threshold_Goods / VAT_Threshold_Services. | I33: Income Tax Act, 2015 (Act 896), as amended; Ghana Revenue Authority — Withholding Tax page | J33: Sections 114–120 and First Schedule, paragraph 8 — GHS 2,000 contract rule | K33: Statute | L33: https://gra.gov.gh/domestic-tax/tax-types/withholding-tax/
B35: C. CONTROL CHECKS — all must read OK before the workbook is relied on
B36: Control check | D36: Expected | E36: Actual | F36: Status
B37: 1. Combined VAT & levy rate agrees to the 20% effective rate published by GRA | D37: 0.2 | E37: =D25 -> 0.2 | F37: =IF(ABS(E37-D37)<0.000001,"OK","REVIEW") -> OK
B38: 2. COVID-19 Health Recovery Levy is nil for the simulation period | D38: 0 | E38: =D23 -> 0 | F38: =IF(E38=D38,"OK","REVIEW") -> OK
B39: 3. Simulation period falls entirely inside the Act 1151 effective window | D39: Yes | E39: =IF(AND(D10>=F20,D11>=F20),"Yes","No") -> Yes | F39: =IF(E39=D39,"OK","REVIEW") -> OK
B40: 4. Every rate and threshold carries a primary source document | D40: 0 | E40: =COUNTBLANK(I20:I33) -> 0 | F40: =IF(E40=D40,"OK","REVIEW") -> OK
B41: 5. Every rate and threshold carries a section / provision reference | D41: 0 | E41: =COUNTBLANK(J20:J33) -> 0 | F41: =IF(E41=D41,"OK","REVIEW") -> OK
B42: 6. No rate, threshold or status cell has been left blank | D42: 0 | E42: =COUNTBLANK(D20:D33) -> 0 | F42: =IF(E42=D42,"OK","REVIEW") -> OK
B43: 7. Assumptions have been verified within the last 90 days | D43: Current | E43: =IF(TODAY()-D13<=90,"Current","Re-verify") -> Current | F43: =IF(E43=D43,"OK","REVIEW") -> OK
B44: 8. Ledger year agrees to the simulation period | D44: Yes | E44: =IF(AND(D12=YEAR(D10),D12=YEAR(D11)),"Yes","No") -> Yes | F44: =IF(E44=D44,"OK","REVIEW") -> OK
B45: D. BASIS OF PREPARATION, CELL LEGEND & IMPORTANT NOTES
B46: Purpose of this sheet
B47: This is the single point of control for every tax rate and threshold in the workbook. The Ledger, VAT reconciliation, exception report and cash-flow summary all read their rates from Section B by name. To re-rate the whole workbook, change the value in column D only — never edit a transaction formula.
B48: Simulation period and the rates applied
B49: The simulation runs from 1 January to 31 December 2026. The Value Added Tax Act, 2025 (Act 1151) took effect on 1 January 2026, so the rates in force for the whole of the simulation period are those shown as current in Section B. Rates that applied before that date are not used by any calculation.
B50: What changed on 1 January 2026
B51: The 1% COVID-19 Health Recovery Levy was abolished. NHIL and the GETFund Levy were re-coupled to the VAT base, so VAT, NHIL and GETFund are now all charged on the same value instead of being stacked on one another. The old cascading calculation produced an effective burden of about 21.9%; the flat combined rate is now 20%. NHIL and GETFund also became recoverable as input tax.
B52: Points requiring confirmation
B53: The GHS 750,000 registration threshold applies to businesses dealing in GOODS. The company's supply is a haulage SERVICE, and the services threshold of GHS 200,000 is drawn from secondary commentary rather than a GRA publication. It is marked "Confirm w/ GRA" in column K and must be verified before any registration or deregistration decision is taken.
B54: Source hierarchy applied
B55: Rates were taken from the Ghana Revenue Authority and the governing Acts in preference to any other source. Column I records the source document, column J the specific provision, column K the type of source, and column L the reference. Each value in column D also carries a cell note repeating its source. No rate in this workbook has been estimated or assumed.
B56: Review cycle
... B59: CELL LEGEND
B60: Input cell — editable | D60: Blue text on cream fill. The only cells a user should type into.
B61: Calculated cell — locked | D61: Black text. Driven by formula. Protected against overtyping.
B62: Link to another sheet | D62: Green text. Pulls a value from elsewhere in this workbook.
B63: Needs attention | D63: Red on pink. An exception, a failed control check, or a figure awaiting confirmation.
B65: DISCLAIMER — This workbook is a simulated demonstration model built for training, control-design and review purposes. All entity names, counterparties, invoice numbers, amounts and transactions are fictitious. Nothing in it constitutes tax, legal or accounting advice, and it must not be used as the basis for a filing position. Verify every rate, threshold and treatment with the Ghana Revenue Authority or a qualified Ghanaian tax adviser before acting.

Sheet Categories
B1: NKABOM HAULAGE LTD — CORE TAX ENGINE
B2: Sheet 2 of 6 • Tax Category Reference • Controlled list — the Ledger validates against this sheet
B3: SIMULATION ONLY — This sheet sets the tax treatment applied to every Ledger line. Change a code here and every transaction using it re-calculates. Not tax advice.
B5: A. TAX CATEGORY REFERENCE TABLE
B7: Code | C7: Category Name | D7: VAT Class | E7: Direction | F7: Charges VAT | G7: Input Deductible | H7: Plain-language definition | I7: VAT / input-tax treatment | J7: Source document | K7: Section / provision | L7: Rate Named Range | M7: Rate | N7: Recoverable
B8: OUT_STD | C8: Standard-rated sale (output) | D8: Standard-rated | E8: Inflow | F8: Yes | G8: n/a - output | H8: Freight and haulage services the company invoices to customers in Ghana. The normal case for this business. | I8: Charge VAT 15% plus NHIL 2.5% and GETFund 2.5% on the tax-exclusive fee, a combined 20%. Declared as output tax on the monthly VAT return. | J8: Value Added Tax Act, 2025 (Act 1151); GRA VAT tax-type guidance | K8: s.3 - imposition of VAT at the standard rate | L8: Combined_VAT_Rate | M8: {=_xlfn.SWITCH(tbl_Categories[[#This Row],[Code]],"OUT_STD",Combined_VAT_Rate,"IN_STD",Combined_VAT_Rate,"IN_NONDED",Combined_VAT_Rate,"WHT_SVC",WHT_Services,"VAT_WHT",VAT_WHT_Rate,"WHT_GOODS",WHT_Goods,"WHT_WORKS",WHT_Works,0)} -> 0.2 | N8: Yes
B9: WHT_SVC | C9: Standard-rated sale, income tax withheld | D9: Standard-rated | E9: Inflow | F9: Yes | G9: n/a - output | H9: A standard-rated haulage sale where the customer is an income-tax withholding agent and deducts 7.5% from the service fee before paying. | I9: VAT treatment is unchanged - still 20% output tax on the full fee. The 7.5% deduction is income tax, not VAT, and is recovered as a tax credit. Never net it off output VAT. | J9: Value Added Tax Act, 2025 (Act 1151); Income Tax Act, 2015 (Act 896) | K9: First Schedule, paragraph 8 - withholding on service fees | L9: WHT_Services | M9: {=_xlfn.SWITCH(tbl_Categories[[#This Row],[Code]],"OUT_STD",Combined_VAT_Rate,"IN_STD",Combined_VAT_Rate,"IN_NONDED",Combined_VAT_Rate,"WHT_SVC",WHT_Services,"VAT_WHT",VAT_WHT_Rate,"WHT_GOODS",WHT_Goods,"WHT_WORKS",WHT_Works,0)} -> 0.075 | N9: No
B10: VAT_WHT | C10: Standard-rated sale, VAT withheld at source | D10: Standard-rated | E10: Inflow | F10: Yes | G10: n/a - output | H10: A standard-rated haulage sale to a customer GRA has appointed as a VAT withholding agent. The customer retains 7% of the taxable value and pays it to GRA directly. | I10: Output tax is still declared in full at 20%. The 7% withheld is a payment on account, claimed as a credit against the VAT liability on production of the withholding certificate. | J10: Value Added Tax Act, 2025 (Act 1151); GRA VAT Withholding guidance | K10: Act 1151 s.56, withholding of 7%; s.55, appointment of agents, confirm in Act text | L10: VAT_WHT_Rate | M10: {=_xlfn.SWITCH(tbl_Categories[[#This Row],[Code]],"OUT_STD",Combined_VAT_Rate,"IN_STD",Combined_VAT_Rate,"IN_NONDED",Combined_VAT_Rate,"WHT_SVC",WHT_Services,"VAT_WHT",VAT_WHT_Rate,"WHT_GOODS",WHT_Goods,"WHT_WORKS",WHT_Works,0)} -> 0.07 | N10: No
B11: IN_STD | C11: Standard-rated purchase (recoverable input) | D11: Standard-rated | E11: Outflow | F11: Yes | G11: Yes | H11: Purchases from VAT-registered suppliers used in making taxable supplies - spares, tyres, repairs, telecoms, professional fees. | I11: Input tax at 20% is recoverable in full and offset against output VAT. From 1 January 2026 the NHIL and GETFund elements are also recoverable, because Act 1151 re-coupled them to the VAT base. | J11: Value Added Tax Act, 2025 (Act 1151); GRA VAT tax-type guidance | K11: Deduction of input tax; re-coupling of NHIL and GETFund | L11: Combined_VAT_Rate | M11: {=_xlfn.SWITCH(tbl_Categories[[#This Row],[Code]],"OUT_STD",Combined_VAT_Rate,"IN_STD",Combined_VAT_Rate,"IN_NONDED",Combined_VAT_Rate,"WHT_SVC",WHT_Services,"VAT_WHT",VAT_WHT_Rate,"WHT_GOODS",WHT_Goods,"WHT_WORKS",WHT_Works,0)} -> 0.2 | N11: Yes
B12: IN_EXEMPT | C12: Exempt purchase | D12: Exempt | E12: Outflow | F12: No | G12: No | H12: Supplies that carry no VAT at all - in this business mainly petroleum products bought for own use, insurance premiums and bank charges. | I12: No VAT is charged by the supplier, so there is no input tax to claim. The full cost is expensed. Claiming input tax on these is a common and material error. | J12: Value Added Tax Act, 2025 (Act 1151) - exempt supplies | K12: Exempt supplies schedule - confirm item in Act text | L12: None - exempt | M12: {=_xlfn.SWITCH(tbl_Categories[[#This Row],[Code]],"OUT_STD",Combined_VAT_Rate,"IN_STD",Combined_VAT_Rate,"IN_NONDED",Combined_VAT_Rate,"WHT_SVC",WHT_Services,"VAT_WHT",VAT_WHT_Rate,"WHT_GOODS",WHT_Goods,"WHT_WORKS",WHT_Works,0)} -> 0 | N12: No
B13: NO_VAT | C13: Outside the scope of VAT | D13: Outside scope | E13: Outflow | F13: No | G13: No | H13: Payments that are not a supply of goods or services - salaries and wages, loan principal and interest, tax remittances, dividends and internal transfers. | I13: Not a taxable transaction. No VAT, no input tax and no entry on the VAT return. Included in the Ledger only so the cash-flow statement is complete. | J13: Value Added Tax Act, 2025 (Act 1151) - scope of the tax | K13: Scope - taxable supply made in Ghana by a taxable person | L13: None - outside scope | M13: {=_xlfn.SWITCH(tbl_Categories[[#This Row],[Code]],"OUT_STD",Combined_VAT_Rate,"IN_STD",Combined_VAT_Rate,"IN_NONDED",Combined_VAT_Rate,"WHT_SVC",WHT_Services,"VAT_WHT",VAT_WHT_Rate,"WHT_GOODS",WHT_Goods,"WHT_WORKS",WHT_Works,0)} -> 0 | N13: No
B14: IN_NONDED | C14: Non-deductible input | D14: Non-deductible | E14: Outflow | F14: Yes | G14: No | H14: Purchases where the supplier correctly charges VAT but the law blocks recovery - entertainment, staff hospitality and passenger vehicles. | I14: VAT at 20% is charged and paid, but none of it may be claimed as input tax. The VAT becomes part of the cost. This is the trap the Error_Flags sheet is designed to catch. | J14: Value Added Tax Act, 2025 (Act 1151) - restriction on input tax | K14: Blocked input tax - entertainment and passenger vehicles; confirm in Act text | L14: Combined_VAT_Rate | M14: {=_xlfn.SWITCH(tbl_Categories[[#This Row],[Code]],"OUT_STD",Combined_VAT_Rate,"IN_STD",Combined_VAT_Rate,"IN_NONDED",Combined_VAT_Rate,"WHT_SVC",WHT_Services,"VAT_WHT",VAT_WHT_Rate,"WHT_GOODS",WHT_Goods,"WHT_WORKS",WHT_Works,0)} -> 0.2 | N14: No
B15: ZERO_RATED | C15: Zero-rated supply | D15: Zero-rated | E15: Inflow | F15: No | G15: Yes | H15: Taxable supplies charged at 0% - chiefly exports qualifying under the Act. Held here for completeness; the simulated Ledger contains none. Charges VAT is set to No because the rate is 0%. Unlike an exempt supply, input tax on related costs stays recoverable - see Input Deductible. | I15: VAT is charged at 0%, so no output tax arises, but the supply stays taxable. Input tax on related costs remains fully recoverable - the key difference from an exempt supply. | J15: Value Added Tax Act, 2025 (Act 1151) - zero-rated supplies | K15: Zero-rating schedule - exports; confirm item in Act text | L15: None - zero-rated | M15: {=_xlfn.SWITCH(tbl_Categories[[#This Row],[Code]],"OUT_STD",Combined_VAT_Rate,"IN_STD",Combined_VAT_Rate,"IN_NONDED",Combined_VAT_Rate,"WHT_SVC",WHT_Services,"VAT_WHT",VAT_WHT_Rate,"WHT_GOODS",WHT_Goods,"WHT_WORKS",WHT_Works,0)} -> 0 | N15: No
B16: WHT_GOODS | C16: Purchase of goods with income tax withheld | D16: Standard-rated (input) | E16: Outflow | F16: Yes | G16: Yes | H16: A standard-rated purchase of goods from a resident supplier where the company must deduct income tax at source before paying. The VAT position and the withholding position are separate: VAT is charged on the supply in the normal way, while income tax is withheld from the payment. | I16: Input VAT, NHIL and GETFund are recoverable in the normal way. The amount withheld is an income tax credit for the supplier, not a reduction of VAT. Withhold only once cumulative payments to the supplier pass the GHS 2,000 annual threshold. | J16: Income Tax Act, 2015 (Act 896), as amended | K16: First Schedule, paragraph 8 — withholding on supply of goods | L16: WHT_Goods | M16: {=_xlfn.SWITCH(tbl_Categories[[#This Row],[Code]],"OUT_STD",Combined_VAT_Rate,"IN_STD",Combined_VAT_Rate,"IN_NONDED",Combined_VAT_Rate,"WHT_SVC",WHT_Services,"VAT_WHT",VAT_WHT_Rate,"WHT_GOODS",WHT_Goods,"WHT_WORKS",WHT_Works,0)} -> 0.03 | N16: No
B17: WHT_WORKS | C17: Works contract with income tax withheld | D17: Standard-rated (input) | E17: Outflow | F17: Yes | G17: Yes | H17: A standard-rated works contract, such as depot civil works or tank construction, from which the company must deduct income tax at source before paying the contractor. | I17: Input VAT, NHIL and GETFund are recoverable in the normal way. The amount withheld is an income tax credit for the contractor and does not affect the VAT return. Subject to the same GHS 2,000 cumulative threshold. | J17: Income Tax Act, 2015 (Act 896), as amended | K17: First Schedule, paragraph 8 — withholding on works | L17: WHT_Works | M17: {=_xlfn.SWITCH(tbl_Categories[[#This Row],[Code]],"OUT_STD",Combined_VAT_Rate,"IN_STD",Combined_VAT_Rate,"IN_NONDED",Combined_VAT_Rate,"WHT_SVC",WHT_Services,"VAT_WHT",VAT_WHT_Rate,"WHT_GOODS",WHT_Goods,"WHT_WORKS",WHT_Works,0)} -> 0.05 | N17: No
B18: OUT_EXEMPT | C18: Exempt supply made by the company | D18: Exempt (output) | E18: Inflow | F18: No | G18: No | H18: A sale by the company that is exempt from VAT, so no VAT, NHIL or GETFund is charged to the customer and none appears on the invoice. | I18: No output tax arises. Unlike a zero-rated supply, input tax attributable to making this supply is NOT recoverable and must be excluded from the input tax claim, which may require an apportionment where the company makes both exempt and taxable supplies. | J18: Value Added Tax Act, 2025 (Act 1151) | K18: Exempt supplies — First Schedule (exempt supplies list) | L18: None - exempt | M18: {=_xlfn.SWITCH(tbl_Categories[[#This Row],[Code]],"OUT_STD",Combined_VAT_Rate,"IN_STD",Combined_VAT_Rate,"IN_NONDED",Combined_VAT_Rate,"WHT_SVC",WHT_Services,"VAT_WHT",VAT_WHT_Rate,"WHT_GOODS",WHT_Goods,"WHT_WORKS",WHT_Works,0)} -> 0 | N18: No

Sheet Ledger
B1: NKABOM HAULAGE LTD — CORE TAX ENGINE
B2: Sheet 3 of 6 • Transaction Ledger • 1 January to 31 August 2026 • 300 simulated transactions
B3: SIMULATION ONLY — All counterparties, invoice numbers and amounts are fictitious. Blue cells are captured data. Grey cells are calculated — do not overtype. Tax Category is validated against the Categories sheet.
B5: A. TRANSACTION LEDGER
B6: All amounts in GHS. Amount is tax-exclusive. Tax Charged on Invoice is the figure as recorded on the source document — it is deliberately NOT a formula, so Error_Flags can compare it against the Expected columns.
B7: Row ID | C7: Date | D7: Description | E7: Counterparty | F7: Direction | G7: Tax Category | H7: Amount | I7: Invoice Number | J7: Tax Charged on Invoice | K7: Expected VAT | L7: Expected NHIL | M7: Expected GETFund | N7: Expected Total Tax | O7: Gross Amount
B8: 1 | C8: 46023 | D8: Bulk haulage of ATK, Kumasi-Sunyani, 9 trips | E8: Golden Harmattan Energy Ltd | F8: Inflow | G8: OUT_STD | H8: 19979 | I8: NHL-2026-0001 | J8: 3995.8 | K8: =IF(INDEX(Cat_ChargesVAT,MATCH(tbl_Ledger[[#This Row],[Tax Category]],Cat_Codes,0))="No",0,tbl_Ledger[[#This Row],[Amount]]*VAT_Rate) -> 2996.85 | L8: =IF(INDEX(Cat_ChargesVAT,MATCH(tbl_Ledger[[#This Row],[Tax Category]],Cat_Codes,0))="No",0,tbl_Ledger[[#This Row],[Amount]]*NHIL_Rate) -> 499.475 | M8: =IF(INDEX(Cat_ChargesVAT,MATCH(tbl_Ledger[[#This Row],[Tax Category]],Cat_Codes,0))="No",0,tbl_Ledger[[#This Row],[Amount]]*GETFund_Rate) -> 499.475 | N8: =tbl_Ledger[[#This Row],[Expected VAT]]+tbl_Ledger[[#This Row],[Expected NHIL]]+tbl_Ledger[[#This Row],[Expected GETFund]] -> 3995.8 | O8: =tbl_Ledger[[#This Row],[Amount]]+tbl_Ledger[[#This Row],[Tax Charged on Invoice]] -> 23974.8
B9: 2 | C9: 46025 | D9: Bulk haulage of ATK, Tema-Takoradi, 3 trips | E9: Tema Bulk Energy Ltd | F9: Inflow | G9: OUT_STD | H9: 63242 | I9: NHL-2026-0002 | J9: 12648.4 | K9: =IF(INDEX(Cat_ChargesVAT,MATCH(tbl_Ledger[[#This Row],[Tax Category]],Cat_Codes,0))="No",0,tbl_Ledger[[#This Row],[Amount]]*VAT_Rate) -> 9486.3 | L9: =IF(INDEX(Cat_ChargesVAT,MATCH(tbl_Ledger[[#This Row],[Tax Category]],Cat_Codes,0))="No",0,tbl_Ledger[[#This Row],[Amount]]*NHIL_Rate) -> 1581.05 | M9: =IF(INDEX(Cat_ChargesVAT,MATCH(tbl_Ledger[[#This Row],[Tax Category]],Cat_Codes,0))="No",0,tbl_Ledger[[#This Row],[Amount]]*GETFund_Rate) -> 1581.05 | N9: =tbl_Ledger[[#This Row],[Expected VAT]]+tbl_Ledger[[#This Row],[Expected NHIL]]+tbl_Ledger[[#This Row],[Expected GETFund]] -> 12648.4 | O9: =tbl_Ledger[[#This Row],[Amount]]+tbl_Ledger[[#This Row],[Tax Charged on Invoice]] -> 75890.4
B10: 3 | C10: 46026 | D10: Mobile and data services | E10: Sahara Fleet Services Ltd | F10: Outflow | G10: IN_STD | H10: 1670 | I10: SIN-2026-0001 | J10: 334 | K10: =IF(INDEX(Cat_ChargesVAT,MATCH(tbl_Ledger[[#This Row],[Tax Category]],Cat_Codes,0))="No",0,tbl_Ledger[[#This Row],[Amount]]*VAT_Rate) -> 250.5 | L10: =IF(INDEX(Cat_ChargesVAT,MATCH(tbl_Ledger[[#This Row],[Tax Category]],Cat_Codes,0))="No",0,tbl_Ledger[[#This Row],[Amount]]*NHIL_Rate) -> 41.75 | M10: =IF(INDEX(Cat_ChargesVAT,MATCH(tbl_Ledger[[#This Row],[Tax Category]],Cat_Codes,0))="No",0,tbl_Ledger[[#This Row],[Amount]]*GETFund_Rate) -> 41.75 | N10: =tbl_Ledger[[#This Row],[Expected VAT]]+tbl_Ledger[[#This Row],[Expected NHIL]]+tbl_Ledger[[#This Row],[Expected GETFund]] -> 334 | O10: =tbl_Ledger[[#This Row],[Amount]]+tbl_Ledger[[#This Row],[Tax Charged on Invoice]] -> 2004
B11: 4 | C11: 46027 | D11: Contract haulage of PMS, Tema-Ho; customer withheld income tax at 7.5% on the service fee | E11: Tema Bulk Energy Ltd | F11: Inflow | G11: WHT_SVC | H11: 68614 | I11: NHL-2026-0003 | J11: 13722.8 | K11: =IF(INDEX(Cat_ChargesVAT,MATCH(tbl_Ledger[[#This Row],[Tax Category]],Cat_Codes,0))="No",0,tbl_Ledger[[#This Row],[Amount]]*VAT_Rate) -> 10292.1 | L11: =IF(INDEX(Cat_ChargesVAT,MATCH(tbl_Ledger[[#This Row],[Tax Category]],Cat_Codes,0))="No",0,tbl_Ledger[[#This Row],[Amount]]*NHIL_Rate) -> 1715.35 | M11: =IF(INDEX(Cat_ChargesVAT,MATCH(tbl_Ledger[[#This Row],[Tax Category]],Cat_Codes,0))="No",0,tbl_Ledger[[#This Row],[Amount]]*GETFund_Rate) -> 1715.35 | N11: =tbl_Ledger[[#This Row],[Expected VAT]]+tbl_Ledger[[#This Row],[Expected NHIL]]+tbl_Ledger[[#This Row],[Expected GETFund]] -> 13722.8 | O11: =tbl_Ledger[[#This Row],[Amount]]+tbl_Ledger[[#This Row],[Tax Charged on Invoice]] -> 82336.8
B12: 5 | C12: 46028 | D12: Bulk haulage of AGO, Tema-Bolgatanga, 2 trips | E12: Sankofa Petroleum Depot Ltd | F12: Inflow | G12: OUT_STD | H12: 66547 | I12: NHL-2026-0004 | J12: 13309.4 | K12: =IF(INDEX(Cat_ChargesVAT,MATCH(tbl_Ledger[[#This Row],[Tax Category]],Cat_Codes,0))="No",0,tbl_Ledger[[#This Row],[Amount]]*VAT_Rate) -> 9982.05 | L12: =IF(INDEX(Cat_ChargesVAT,MATCH(tbl_Ledger[[#This Row],[Tax Category]],Cat_Codes,0))="No",0,tbl_Ledger[[#This Row],[Amount]]*NHIL_Rate) -> 1663.675 | M12: =IF(INDEX(Cat_ChargesVAT,MATCH(tbl_Ledger[[#This Row],[Tax Category]],Cat_Codes,0))="No",0,tbl_Ledger[[#This Row],[Amount]]*GETFund_Rate) -> 1663.675 | N12: =tbl_Ledger[[#This Row],[Expected VAT]]+tbl_Ledger[[#This Row],[Expected NHIL]]+tbl_Ledger[[#This Row],[Expected GETFund]] -> 13309.4 | O12: =tbl_Ledger[[#This Row],[Amount]]+tbl_Ledger[[#This Row],[Tax Charged on Invoice]] -> 79856.4
B13: 6 | C13: 46028 | D13: Contract haulage of AGO, Tema-Bolgatanga; customer withheld income tax at 7.5% on the service fee | E13: Tema Bulk Energy Ltd | F13: Inflow | G13: WHT_SVC | H13: 58678 | I13: NHL-2026-0005 | J13: 11735.6 | K13: =IF(INDEX(Cat_ChargesVAT,MATCH(tbl_Ledger[[#This Row],[Tax Category]],Cat_Codes,0))="No",0,tbl_Ledger[[#This Row],[Amount]]*VAT_Rate) -> 8801.7 | L13: =IF(INDEX(Cat_ChargesVAT,MATCH(tbl_Ledger[[#This Row],[Tax Category]],Cat_Codes,0))="No",0,tbl_Ledger[[#This Row],[Amount]]*NHIL_Rate) -> 1466.95 | M13: =IF(INDEX(Cat_ChargesVAT,MATCH(tbl_Ledger[[#This Row],[Tax Category]],Cat_Codes,0))="No",0,tbl_Ledger[[#This Row],[Amount]]*GETFund_Rate) -> 1466.95 | N13: =tbl_Ledger[[#This Row],[Expected VAT]]+tbl_Ledger[[#This Row],[Expected NHIL]]+tbl_Ledger[[#This Row],[Expected GETFund]] -> 11735.6 | O13: =tbl_Ledger[[#This Row],[Amount]]+tbl_Ledger[[#This Row],[Tax Charged on Invoice]] -> 70413.6
B14: 7 | C14: 46029 | D14: Bulk haulage of AGO, Takoradi-Wa, 7 trips | E14: Golden Harmattan Energy Ltd | F14: Inflow | G14: OUT_STD | H14: 90933 | I14: NHL-2026-0006 | J14: 18186.6 | K14: =IF(INDEX(Cat_ChargesVAT,MATCH(tbl_Ledger[[#This Row],[Tax Category]],Cat_Codes,0))="No",0,tbl_Ledger[[#This Row],[Amount]]*VAT_Rate) -> 13639.95 | L14: =IF(INDEX(Cat_ChargesVAT,MATCH(tbl_Ledger[[#This Row],[Tax Category]],Cat_Codes,0))="No",0,tbl_Ledger[[#This Row],[Amount]]*NHIL_Rate) -> 2273.325 | M14: =IF(INDEX(Cat_ChargesVAT,MATCH(tbl_Ledger[[#This Row],[Tax Category]],Cat_Codes,0))="No",0,tbl_Ledger[[#This Row],[Amount]]*GETFund_Rate) -> 2273.325 | N14: =tbl_Ledger[[#This Row],[Expected VAT]]+tbl_Ledger[[#This Row],[Expected NHIL]]+tbl_Ledger[[#This Row],[Expected GETFund]] -> 18186.6 | O14: =tbl_Ledger[[#This Row],[Amount]]+tbl_Ledger[[#This Row],[Tax Charged on Invoice]] -> 109119.6
B15: 8 | C15: 46032 | D15: Diesel (AGO) purchased for own fleet use, 10,136 litres | E15: Zenith Fuel Depot Ltd | F15: Outflow | G15: IN_EXEMPT | H15: 60137 | I15: SIN-2026-0002 | J15: 0 | K15: =IF(INDEX(Cat_ChargesVAT,MATCH(tbl_Ledger[[#This Row],[Tax Category]],Cat_Codes,0))="No",0,tbl_Ledger[[#This Row],[Amount]]*VAT_Rate) -> 0 | L15: =IF(INDEX(Cat_ChargesVAT,MATCH(tbl_Ledger[[#This Row],[Tax Category]],Cat_Codes,0))="No",0,tbl_Ledger[[#This Row],[Amount]]*NHIL_Rate) -> 0 | M15: =IF(INDEX(Cat_ChargesVAT,MATCH(tbl_Ledger[[#This Row],[Tax Category]],Cat_Codes,0))="No",0,tbl_Ledger[[#This Row],[Amount]]*GETFund_Rate) -> 0 | N15: =tbl_Ledger[[#This Row],[Expected VAT]]+tbl_Ledger[[#This Row],[Expected NHIL]]+tbl_Ledger[[#This Row],[Expected GETFund]] -> 0 | O15: =tbl_Ledger[[#This Row],[Amount]]+tbl_Ledger[[#This Row],[Tax Charged on Invoice]] -> 60137
B16: 9 | C16: 46032 | D16: Diesel (AGO) purchased for own fleet use, 8,242 litres | E16: Zenith Fuel Depot Ltd | F16: Outflow | G16: IN_EXEMPT | H16: 44086 | I16: SIN-2026-0003 | J16: 0 | K16: =IF(INDEX(Cat_ChargesVAT,MATCH(tbl_Ledger[[#This Row],[Tax Category]],Cat_Codes,0))="No",0,tbl_Ledger[[#This Row],[Amount]]*VAT_Rate) -> 0 | L16: =IF(INDEX(Cat_ChargesVAT,MATCH(tbl_Ledger[[#This Row],[Tax Category]],Cat_Codes,0))="No",0,tbl_Ledger[[#This Row],[Amount]]*NHIL_Rate) -> 0 | M16: =IF(INDEX(Cat_ChargesVAT,MATCH(tbl_Ledger[[#This Row],[Tax Category]],Cat_Codes,0))="No",0,tbl_Ledger[[#This Row],[Amount]]*GETFund_Rate) -> 0 | N16: =tbl_Ledger[[#This Row],[Expected VAT]]+tbl_Ledger[[#This Row],[Expected NHIL]]+tbl_Ledger[[#This Row],[Expected GETFund]] -> 0 | O16: =tbl_Ledger[[#This Row],[Amount]]+tbl_Ledger[[#This Row],[Tax Charged on Invoice]] -> 44086
B17: 10 | C17: 46034 | D17: Diesel (AGO) purchased for own fleet use, 16,629 litres | E17: Zenith Fuel Depot Ltd | F17: Outflow | G17: IN_EXEMPT | H17: 77769 | I17: SIN-2026-0004 | J17: 0 | K17: =IF(INDEX(Cat_ChargesVAT,MATCH(tbl_Ledger[[#This Row],[Tax Category]],Cat_Codes,0))="No",0,tbl_Ledger[[#This Row],[Amount]]*VAT_Rate) -> 0 | L17: =IF(INDEX(Cat_ChargesVAT,MATCH(tbl_Ledger[[#This Row],[Tax Category]],Cat_Codes,0))="No",0,tbl_Ledger[[#This Row],[Amount]]*NHIL_Rate) -> 0 | M17: =IF(INDEX(Cat_ChargesVAT,MATCH(tbl_Ledger[[#This Row],[Tax Category]],Cat_Codes,0))="No",0,tbl_Ledger[[#This Row],[Amount]]*GETFund_Rate) -> 0 | N17: =tbl_Ledger[[#This Row],[Expected VAT]]+tbl_Ledger[[#This Row],[Expected NHIL]]+tbl_Ledger[[#This Row],[Expected GETFund]] -> 0 | O17: =tbl_Ledger[[#This Row],[Amount]]+tbl_Ledger[[#This Row],[Tax Charged on Invoice]] -> 77769
B18: 11 | C18: 46036 | D18: PAYE and SSNIT contributions - January | E18: Ghana Revenue Authority | F18: Outflow | G18: NO_VAT | H18: 25595 | I18: GRA-2026-0001 | J18: 0 | K18: =IF(INDEX(Cat_ChargesVAT,MATCH(tbl_Ledger[[#This Row],[Tax Category]],Cat_Codes,0))="No",0,tbl_Ledger[[#This Row],[Amount]]*VAT_Rate) -> 0 | L18: =IF(INDEX(Cat_ChargesVAT,MATCH(tbl_Ledger[[#This Row],[Tax Category]],Cat_Codes,0))="No",0,tbl_Ledger[[#This Row],[Amount]]*NHIL_Rate) -> 0 | M18: =IF(INDEX(Cat_ChargesVAT,MATCH(tbl_Ledger[[#This Row],[Tax Category]],Cat_Codes,0))="No",0,tbl_Ledger[[#This Row],[Amount]]*GETFund_Rate) -> 0 | N18: =tbl_Ledger[[#This Row],[Expected VAT]]+tbl_Ledger[[#This Row],[Expected NHIL]]+tbl_Ledger[[#This Row],[Expected GETFund]] -> 0 | O18: =tbl_Ledger[[#This Row],[Amount]]+tbl_Ledger[[#This Row],[Tax Charged on Invoice]] -> 25595
B19: 12 | C19: 46037 | D19: Term loan repayment - principal and interest, instalment 1 | E19: Meridian Bank Ghana Ltd | F19: Outflow | G19: NO_VAT | H19: 41833 | I19: LN-2026-0001 | J19: 0 | K19: =IF(INDEX(Cat_ChargesVAT,MATCH(tbl_Ledger[[#This Row],[Tax Category]],Cat_Codes,0))="No",0,tbl_Ledger[[#This Row],[Amount]]*VAT_Rate) -> 0 | L19: =IF(INDEX(Cat_ChargesVAT,MATCH(tbl_Ledger[[#This Row],[Tax Category]],Cat_Codes,0))="No",0,tbl_Ledger[[#This Row],[Amount]]*NHIL_Rate) -> 0 | M19: =IF(INDEX(Cat_ChargesVAT,MATCH(tbl_Ledger[[#This Row],[Tax Category]],Cat_Codes,0))="No",0,tbl_Ledger[[#This Row],[Amount]]*GETFund_Rate) -> 0 | N19: =tbl_Ledger[[#This Row],[Expected VAT]]+tbl_Ledger[[#This Row],[Expected NHIL]]+tbl_Ledger[[#This Row],[Expected GETFund]] -> 0 | O19: =tbl_Ledger[[#This Row],[Amount]]+tbl_Ledger[[#This Row],[Tax Charged on Invoice]] -> 41833
... B99: 92 | C99: 46094 | D99: Term haulage contract, ATK, Tema-Bolgatanga; customer is an appointed VAT withholding agent and retained 7% | E99: Northern Star BDC Ltd | F99: Inflow | G99: VAT_WHT | H99: 79662 | I99: NHL-2026-0043 | J99: 15932.4 | K99: =IF(INDEX(Cat_ChargesVAT,MATCH(tbl_Ledger[[#This Row],[Tax Category]],Cat_Codes,0))="No",0,tbl_Ledger[[#This Row],[Amount]]*VAT_Rate) -> 11949.3 | L99: =IF(INDEX(Cat_ChargesVAT,MATCH(tbl_Ledger[[#This Row],[Tax Category]],Cat_Codes,0))="No",0,tbl_Ledger[[#This Row],[Amount]]*NHIL_Rate) -> 1991.55 | M99: =IF(INDEX(Cat_ChargesVAT,MATCH(tbl_Ledger[[#This Row],[Tax Category]],Cat_Codes,0))="No",0,tbl_Ledger[[#This Row],[Amount]]*GETFund_Rate) -> 1991.55 | N99: =tbl_Ledger[[#This Row],[Expected VAT]]+tbl_Ledger[[#This Row],[Expected NHIL]]+tbl_Ledger[[#This Row],[Expected GETFund]] -> 15932.4 | O99: =tbl_Ledger[[#This Row],[Amount]]+tbl_Ledger[[#This Row],[Tax Charged on Invoice]] -> 95594.4
B100: 93 | C100: 46095 | D100: Bulk haulage of AGO, Tema-Cape Coast, 6 trips | E100: Northern Star BDC Ltd | F100: Inflow | G100: OUT_STD | H100: 92487 | J100: 18497.4 | K100: =IF(INDEX(Cat_ChargesVAT,MATCH(tbl_Ledger[[#This Row],[Tax Category]],Cat_Codes,0))="No",0,tbl_Ledger[[#This Row],[Amount]]*VAT_Rate) -> 13873.05 | L100: =IF(INDEX(Cat_ChargesVAT,MATCH(tbl_Ledger[[#This Row],[Tax Category]],Cat_Codes,0))="No",0,tbl_Ledger[[#This Row],[Amount]]*NHIL_Rate) -> 2312.175 | M100: =IF(INDEX(Cat_ChargesVAT,MATCH(tbl_Ledger[[#This Row],[Tax Category]],Cat_Codes,0))="No",0,tbl_Ledger[[#This Row],[Amount]]*GETFund_Rate) -> 2312.175 | N100: =tbl_Ledger[[#This Row],[Expected VAT]]+tbl_Ledger[[#This Row],[Expected NHIL]]+tbl_Ledger[[#This Row],[Expected GETFund]] -> 18497.4 | O100: =tbl_Ledger[[#This Row],[Amount]]+tbl_Ledger[[#This Row],[Tax Charged on Invoice]] -> 110984.4
B101: 94 | C101: 46096 | D101: Passenger vehicle running costs - management car | E101: Sunset Lounge Ltd | F101: Outflow | G101: IN_NONDED | H101: 1960 | I101: SIN-2026-0031 | J101: 392 | K101: =IF(INDEX(Cat_ChargesVAT,MATCH(tbl_Ledger[[#This Row],[Tax Category]],Cat_Codes,0))="No",0,tbl_Ledger[[#This Row],[Amount]]*VAT_Rate) -> 294 | L101: =IF(INDEX(Cat_ChargesVAT,MATCH(tbl_Ledger[[#This Row],[Tax Category]],Cat_Codes,0))="No",0,tbl_Ledger[[#This Row],[Amount]]*NHIL_Rate) -> 49 | M101: =IF(INDEX(Cat_ChargesVAT,MATCH(tbl_Ledger[[#This Row],[Tax Category]],Cat_Codes,0))="No",0,tbl_Ledger[[#This Row],[Amount]]*GETFund_Rate) -> 49 | N101: =tbl_Ledger[[#This Row],[Expected VAT]]+tbl_Ledger[[#This Row],[Expected NHIL]]+tbl_Ledger[[#This Row],[Expected GETFund]] -> 392 | O101: =tbl_Ledger[[#This Row],[Amount]]+tbl_Ledger[[#This Row],[Tax Charged on Invoice]] -> 2352
B102: 95 | C102: 46096 | D102: Workshop consumables and lubricants | E102: Adom Telecom Ghana Ltd | F102: Outflow | G102: IN_STD | H102: 8703 | I102: SIN-2026-0032 | J102: 1740.6 | K102: =IF(INDEX(Cat_ChargesVAT,MATCH(tbl_Ledger[[#This Row],[Tax Category]],Cat_Codes,0))="No",0,tbl_Ledger[[#This Row],[Amount]]*VAT_Rate) -> 1305.45 | L102: =IF(INDEX(Cat_ChargesVAT,MATCH(tbl_Ledger[[#This Row],[Tax Category]],Cat_Codes,0))="No",0,tbl_Ledger[[#This Row],[Amount]]*NHIL_Rate) -> 217.575 | M102: =IF(INDEX(Cat_ChargesVAT,MATCH(tbl_Ledger[[#This Row],[Tax Category]],Cat_Codes,0))="No",0,tbl_Ledger[[#This Row],[Amount]]*GETFund_Rate) -> 217.575 | N102: =tbl_Ledger[[#This Row],[Expected VAT]]+tbl_Ledger[[#This Row],[Expected NHIL]]+tbl_Ledger[[#This Row],[Expected GETFund]] -> 1740.6 | O102: =tbl_Ledger[[#This Row],[Amount]]+tbl_Ledger[[#This Row],[Tax Charged on Invoice]] -> 10443.6
B103: 96 | C103: 46096 | D103: Term loan repayment - principal and interest, instalment 3 | E103: Meridian Bank Ghana Ltd | F103: Outflow | G103: NO_VAT | H103: 44143 | I103: LN-2026-0003 | J103: 0 | K103: =IF(INDEX(Cat_ChargesVAT,MATCH(tbl_Ledger[[#This Row],[Tax Category]],Cat_Codes,0))="No",0,tbl_Ledger[[#This Row],[Amount]]*VAT_Rate) -> 0 | L103: =IF(INDEX(Cat_ChargesVAT,MATCH(tbl_Ledger[[#This Row],[Tax Category]],Cat_Codes,0))="No",0,tbl_Ledger[[#This Row],[Amount]]*NHIL_Rate) -> 0 | M103: =IF(INDEX(Cat_ChargesVAT,MATCH(tbl_Ledger[[#This Row],[Tax Category]],Cat_Codes,0))="No",0,tbl_Ledger[[#This Row],[Amount]]*GETFund_Rate) -> 0 | N103: =tbl_Ledger[[#This Row],[Expected VAT]]+tbl_Ledger[[#This Row],[Expected NHIL]]+tbl_Ledger[[#This Row],[Expected GETFund]] -> 0 | O103: =tbl_Ledger[[#This Row],[Amount]]+tbl_Ledger[[#This Row],[Tax Charged on Invoice]] -> 44143
B104: 97 | C104: 46096 | D104: Bulk haulage of AGO, Takoradi-Wa, 7 trips | E104: Pra River Energy Ltd | F104: Inflow | G104: OUT_STD | H104: 59848 | I104: NHL-2026-0045 | J104: 11969.6 | K104: =IF(INDEX(Cat_ChargesVAT,MATCH(tbl_Ledger[[#This Row],[Tax Category]],Cat_Codes,0))="No",0,tbl_Ledger[[#This Row],[Amount]]*VAT_Rate) -> 8977.2 | L104: =IF(INDEX(Cat_ChargesVAT,MATCH(tbl_Ledger[[#This Row],[Tax Category]],Cat_Codes,0))="No",0,tbl_Ledger[[#This Row],[Amount]]*NHIL_Rate) -> 1496.2 | M104: =IF(INDEX(Cat_ChargesVAT,MATCH(tbl_Ledger[[#This Row],[Tax Category]],Cat_Codes,0))="No",0,tbl_Ledger[[#This Row],[Amount]]*GETFund_Rate) -> 1496.2 | N104: =tbl_Ledger[[#This Row],[Expected VAT]]+tbl_Ledger[[#This Row],[Expected NHIL]]+tbl_Ledger[[#This Row],[Expected GETFund]] -> 11969.6 | O104: =tbl_Ledger[[#This Row],[Amount]]+tbl_Ledger[[#This Row],[Tax Charged on Invoice]] -> 71817.6
B105: 98 | C105: 46098 | D105: Diesel (AGO) purchased for own fleet use, 17,746 litres | E105: Zenith Fuel Depot Ltd | F105: Outflow | G105: IN_EXEMPT | H105: 52490 | I105: SIN-2026-0033 | J105: 0 | K105: =IF(INDEX(Cat_ChargesVAT,MATCH(tbl_Ledger[[#This Row],[Tax Category]],Cat_Codes,0))="No",0,tbl_Ledger[[#This Row],[Amount]]*VAT_Rate) -> 0 | L105: =IF(INDEX(Cat_ChargesVAT,MATCH(tbl_Ledger[[#This Row],[Tax Category]],Cat_Codes,0))="No",0,tbl_Ledger[[#This Row],[Amount]]*NHIL_Rate) -> 0 | M105: =IF(INDEX(Cat_ChargesVAT,MATCH(tbl_Ledger[[#This Row],[Tax Category]],Cat_Codes,0))="No",0,tbl_Ledger[[#This Row],[Amount]]*GETFund_Rate) -> 0 | N105: =tbl_Ledger[[#This Row],[Expected VAT]]+tbl_Ledger[[#This Row],[Expected NHIL]]+tbl_Ledger[[#This Row],[Expected GETFund]] -> 0 | O105: =tbl_Ledger[[#This Row],[Amount]]+tbl_Ledger[[#This Row],[Tax Charged on Invoice]] -> 52490
B106: 99 | C106: 46098 | D106: Workshop consumables and lubricants | E106: Bono Workshop Services Ltd | F106: Outflow | G106: IN_STD | H106: 4906 | I106: SIN-2026-0081 | J106: 981.2 | K106: =IF(INDEX(Cat_ChargesVAT,MATCH(tbl_Ledger[[#This Row],[Tax Category]],Cat_Codes,0))="No",0,tbl_Ledger[[#This Row],[Amount]]*VAT_Rate) -> 735.9 | L106: =IF(INDEX(Cat_ChargesVAT,MATCH(tbl_Ledger[[#This Row],[Tax Category]],Cat_Codes,0))="No",0,tbl_Ledger[[#This Row],[Amount]]*NHIL_Rate) -> 122.65 | M106: =IF(INDEX(Cat_ChargesVAT,MATCH(tbl_Ledger[[#This Row],[Tax Category]],Cat_Codes,0))="No",0,tbl_Ledger[[#This Row],[Amount]]*GETFund_Rate) -> 122.65 | N106: =tbl_Ledger[[#This Row],[Expected VAT]]+tbl_Ledger[[#This Row],[Expected NHIL]]+tbl_Ledger[[#This Row],[Expected GETFund]] -> 981.2 | O106: =tbl_Ledger[[#This Row],[Amount]]+tbl_Ledger[[#This Row],[Tax Charged on Invoice]] -> 5887.2
B107: 100 | C107: 46099 | D107: Contract haulage of ATK, Takoradi-Wa; customer withheld income tax at 7.5% on the service fee | E107: Tema Bulk Energy Ltd | F107: Inflow | G107: WHT_SVC | H107: 49260 | I107: NHL-2026-0046 | J107: 9852 | K107: =IF(INDEX(Cat_ChargesVAT,MATCH(tbl_Ledger[[#This Row],[Tax Category]],Cat_Codes,0))="No",0,tbl_Ledger[[#This Row],[Amount]]*VAT_Rate) -> 7389 | L107: =IF(INDEX(Cat_ChargesVAT,MATCH(tbl_Ledger[[#This Row],[Tax Category]],Cat_Codes,0))="No",0,tbl_Ledger[[#This Row],[Amount]]*NHIL_Rate) -> 1231.5 | M107: =IF(INDEX(Cat_ChargesVAT,MATCH(tbl_Ledger[[#This Row],[Tax Category]],Cat_Codes,0))="No",0,tbl_Ledger[[#This Row],[Amount]]*GETFund_Rate) -> 1231.5 | N107: =tbl_Ledger[[#This Row],[Expected VAT]]+tbl_Ledger[[#This Row],[Expected NHIL]]+tbl_Ledger[[#This Row],[Expected GETFund]] -> 9852 | O107: =tbl_Ledger[[#This Row],[Amount]]+tbl_Ledger[[#This Row],[Tax Charged on Invoice]] -> 59112
B108: 101 | C108: 46100 | D108: Transfer and settlement charges | E108: Meridian Bank Ghana Ltd | F108: Outflow | G108: IN_EXEMPT | H108: 521 | I108: BNK-2026-0010 | J108: 104.2 | K108: =IF(INDEX(Cat_ChargesVAT,MATCH(tbl_Ledger[[#This Row],[Tax Category]],Cat_Codes,0))="No",0,tbl_Ledger[[#This Row],[Amount]]*VAT_Rate) -> 0 | L108: =IF(INDEX(Cat_ChargesVAT,MATCH(tbl_Ledger[[#This Row],[Tax Category]],Cat_Codes,0))="No",0,tbl_Ledger[[#This Row],[Amount]]*NHIL_Rate) -> 0 | M108: =IF(INDEX(Cat_ChargesVAT,MATCH(tbl_Ledger[[#This Row],[Tax Category]],Cat_Codes,0))="No",0,tbl_Ledger[[#This Row],[Amount]]*GETFund_Rate) -> 0 | N108: =tbl_Ledger[[#This Row],[Expected VAT]]+tbl_Ledger[[#This Row],[Expected NHIL]]+tbl_Ledger[[#This Row],[Expected GETFund]] -> 0 | O108: =tbl_Ledger[[#This Row],[Amount]]+tbl_Ledger[[#This Row],[Tax Charged on Invoice]] -> 625.2
B109: 102 | C109: 46100 | D109: Motor fleet insurance premium | E109: Unity Assurance Ltd | F109: Outflow | G109: IN_EXEMPT | H109: 31040 | I109: SIN-2026-0035 | J109: 0 | K109: =IF(INDEX(Cat_ChargesVAT,MATCH(tbl_Ledger[[#This Row],[Tax Category]],Cat_Codes,0))="No",0,tbl_Ledger[[#This Row],[Amount]]*VAT_Rate) -> 0 | L109: =IF(INDEX(Cat_ChargesVAT,MATCH(tbl_Ledger[[#This Row],[Tax Category]],Cat_Codes,0))="No",0,tbl_Ledger[[#This Row],[Amount]]*NHIL_Rate) -> 0 | M109: =IF(INDEX(Cat_ChargesVAT,MATCH(tbl_Ledger[[#This Row],[Tax Category]],Cat_Codes,0))="No",0,tbl_Ledger[[#This Row],[Amount]]*GETFund_Rate) -> 0 | N109: =tbl_Ledger[[#This Row],[Expected VAT]]+tbl_Ledger[[#This Row],[Expected NHIL]]+tbl_Ledger[[#This Row],[Expected GETFund]] -> 0 | O109: =tbl_Ledger[[#This Row],[Amount]]+tbl_Ledger[[#This Row],[Tax Charged on Invoice]] -> 31040
B110: 103 | C110: 46101 | D110: Motor fleet insurance premium | E110: Pillar Insurance Ghana Ltd | F110: Outflow | G110: IN_STD | H110: 21750 | I110: SIN-2026-0036 | J110: 4350 | K110: =IF(INDEX(Cat_ChargesVAT,MATCH(tbl_Ledger[[#This Row],[Tax Category]],Cat_Codes,0))="No",0,tbl_Ledger[[#This Row],[Amount]]*VAT_Rate) -> 3262.5 | L110: =IF(INDEX(Cat_ChargesVAT,MATCH(tbl_Ledger[[#This Row],[Tax Category]],Cat_Codes,0))="No",0,tbl_Ledger[[#This Row],[Amount]]*NHIL_Rate) -> 543.75 | M110: =IF(INDEX(Cat_ChargesVAT,MATCH(tbl_Ledger[[#This Row],[Tax Category]],Cat_Codes,0))="No",0,tbl_Ledger[[#This Row],[Amount]]*GETFund_Rate) -> 543.75 | N110: =tbl_Ledger[[#This Row],[Expected VAT]]+tbl_Ledger[[#This Row],[Expected NHIL]]+tbl_Ledger[[#This Row],[Expected GETFund]] -> 4350 | O110: =tbl_Ledger[[#This Row],[Amount]]+tbl_Ledger[[#This Row],[Tax Charged on Invoice]] -> 26100
B111: 104 | C111: 46104 | D111: Diesel (AGO) purchased for own fleet use, 21,989 litres | E111: Zenith Fuel Depot Ltd | F111: Outflow | G111: IN_EXEMPT | H111: 82343 | I111: SIN-2026-0037 | J111: 0 | K111: =IF(INDEX(Cat_ChargesVAT,MATCH(tbl_Ledger[[#This Row],[Tax Category]],Cat_Codes,0))="No",0,tbl_Ledger[[#This Row],[Amount]]*VAT_Rate) -> 0 | L111: =IF(INDEX(Cat_ChargesVAT,MATCH(tbl_Ledger[[#This Row],[Tax Category]],Cat_Codes,0))="No",0,tbl_Ledger[[#This Row],[Amount]]*NHIL_Rate) -> 0 | M111: =IF(INDEX(Cat_ChargesVAT,MATCH(tbl_Ledger[[#This Row],[Tax Category]],Cat_Codes,0))="No",0,tbl_Ledger[[#This Row],[Amount]]*GETFund_Rate) -> 0 | N111: =tbl_Ledger[[#This Row],[Expected VAT]]+tbl_Ledger[[#This Row],[Expected NHIL]]+tbl_Ledger[[#This Row],[Expected GETFund]] -> 0 | O111: =tbl_Ledger[[#This Row],[Amount]]+tbl_Ledger[[#This Row],[Tax Charged on Invoice]] -> 82343
B112: 105 | C112: 46104 | D112: VAT and levies remitted to GRA for March period | E112: Ghana Revenue Authority | F112: Outflow | G112: NO_VAT | H112: 66914 | I112: GRA-2026-0006 | J112: 0 | K112: =IF(INDEX(Cat_ChargesVAT,MATCH(tbl_Ledger[[#This Row],[Tax Category]],Cat_Codes,0))="No",0,tbl_Ledger[[#This Row],[Amount]]*VAT_Rate) -> 0 | L112: =IF(INDEX(Cat_ChargesVAT,MATCH(tbl_Ledger[[#This Row],[Tax Category]],Cat_Codes,0))="No",0,tbl_Ledger[[#This Row],[Amount]]*NHIL_Rate) -> 0 | M112: =IF(INDEX(Cat_ChargesVAT,MATCH(tbl_Ledger[[#This Row],[Tax Category]],Cat_Codes,0))="No",0,tbl_Ledger[[#This Row],[Amount]]*GETFund_Rate) -> 0 | N112: =tbl_Ledger[[#This Row],[Expected VAT]]+tbl_Ledger[[#This Row],[Expected NHIL]]+tbl_Ledger[[#This Row],[Expected GETFund]] -> 0 | O112: =tbl_Ledger[[#This Row],[Amount]]+tbl_Ledger[[#This Row],[Tax Charged on Invoice]] -> 66914
... B120: 113 | C120: 46110 | D120: Office stationery and printing | E120: Adom Telecom Ghana Ltd | F120: Outflow | G120: IN_STD | H120: 2926 | I120: SIN-2026-0039 | J120: 585.2 | K120: =IF(INDEX(Cat_ChargesVAT,MATCH(tbl_Ledger[[#This Row],[Tax Category]],Cat_Codes,0))="No",0,tbl_Ledger[[#This Row],[Amount]]*VAT_Rate) -> 438.9 | L120: =IF(INDEX(Cat_ChargesVAT,MATCH(tbl_Ledger[[#This Row],[Tax Category]],Cat_Codes,0))="No",0,tbl_Ledger[[#This Row],[Amount]]*NHIL_Rate) -> 73.15 | M120: =IF(INDEX(Cat_ChargesVAT,MATCH(tbl_Ledger[[#This Row],[Tax Category]],Cat_Codes,0))="No",0,tbl_Ledger[[#This Row],[Amount]]*GETFund_Rate) -> 73.15 | N120: =tbl_Ledger[[#This Row],[Expected VAT]]+tbl_Ledger[[#This Row],[Expected NHIL]]+tbl_Ledger[[#This Row],[Expected GETFund]] -> 585.2 | O120: =tbl_Ledger[[#This Row],[Amount]]+tbl_Ledger[[#This Row],[Tax Charged on Invoice]] -> 3511.2
B121: 114 | C121: 46110 | D121: Fleet tracking software subscription | E121: Sahara Fleet Services Ltd | F121: Outflow | G121: IN_STD | H121: 8752 | J121: 1750.4 | K121: =IF(INDEX(Cat_ChargesVAT,MATCH(tbl_Ledger[[#This Row],[Tax Category]],Cat_Codes,0))="No",0,tbl_Ledger[[#This Row],[Amount]]*VAT_Rate) -> 1312.8 | L121: =IF(INDEX(Cat_ChargesVAT,MATCH(tbl_Ledger[[#This Row],[Tax Category]],Cat_Codes,0))="No",0,tbl_Ledger[[#This Row],[Amount]]*NHIL_Rate) -> 218.8 | M121: =IF(INDEX(Cat_ChargesVAT,MATCH(tbl_Ledger[[#This Row],[Tax Category]],Cat_Codes,0))="No",0,tbl_Ledger[[#This Row],[Amount]]*GETFund_Rate) -> 218.8 | N121: =tbl_Ledger[[#This Row],[Expected VAT]]+tbl_Ledger[[#This Row],[Expected NHIL]]+tbl_Ledger[[#This Row],[Expected GETFund]] -> 1750.4 | O121: =tbl_Ledger[[#This Row],[Amount]]+tbl_Ledger[[#This Row],[Tax Charged on Invoice]] -> 10502.4
B122: 115 | C122: 46110 | D122: Bulk haulage of AGO, Kumasi-Sunyani, 9 trips | E122: Golden Harmattan Energy Ltd | F122: Inflow | G122: OUT_STD | H122: 72134 | I122: NHL-2026-0051 | J122: 14426.8 | K122: =IF(INDEX(Cat_ChargesVAT,MATCH(tbl_Ledger[[#This Row],[Tax Category]],Cat_Codes,0))="No",0,tbl_Ledger[[#This Row],[Amount]]*VAT_Rate) -> 10820.1 | L122: =IF(INDEX(Cat_ChargesVAT,MATCH(tbl_Ledger[[#This Row],[Tax Category]],Cat_Codes,0))="No",0,tbl_Ledger[[#This Row],[Amount]]*NHIL_Rate) -> 1803.35 | M122: =IF(INDEX(Cat_ChargesVAT,MATCH(tbl_Ledger[[#This Row],[Tax Category]],Cat_Codes,0))="No",0,tbl_Ledger[[#This Row],[Amount]]*GETFund_Rate) -> 1803.35 | N122: =tbl_Ledger[[#This Row],[Expected VAT]]+tbl_Ledger[[#This Row],[Expected NHIL]]+tbl_Ledger[[#This Row],[Expected GETFund]] -> 14426.8 | O122: =tbl_Ledger[[#This Row],[Amount]]+tbl_Ledger[[#This Row],[Tax Charged on Invoice]] -> 86560.8
B123: 116 | C123: 46112 | D123: Staff salaries and wages - March | E123: Nkabom Haulage Payroll | F123: Outflow | G123: NO_VAT | H123: 119432 | I123: PAY-2026-0003 | J123: 0 | K123: =IF(INDEX(Cat_ChargesVAT,MATCH(tbl_Ledger[[#This Row],[Tax Category]],Cat_Codes,0))="No",0,tbl_Ledger[[#This Row],[Amount]]*VAT_Rate) -> 0 | L123: =IF(INDEX(Cat_ChargesVAT,MATCH(tbl_Ledger[[#This Row],[Tax Category]],Cat_Codes,0))="No",0,tbl_Ledger[[#This Row],[Amount]]*NHIL_Rate) -> 0 | M123: =IF(INDEX(Cat_ChargesVAT,MATCH(tbl_Ledger[[#This Row],[Tax Category]],Cat_Codes,0))="No",0,tbl_Ledger[[#This Row],[Amount]]*GETFund_Rate) -> 0 | N123: =tbl_Ledger[[#This Row],[Expected VAT]]+tbl_Ledger[[#This Row],[Expected NHIL]]+tbl_Ledger[[#This Row],[Expected GETFund]] -> 0 | O123: =tbl_Ledger[[#This Row],[Amount]]+tbl_Ledger[[#This Row],[Tax Charged on Invoice]] -> 119432
B124: 117 | C124: 46113 | D124: Year-end staff function | E124: Executive Motors Ltd | F124: Outflow | G124: IN_NONDED | H124: 1376 | I124: SIN-2026-0041 | J124: 275.2 | K124: =IF(INDEX(Cat_ChargesVAT,MATCH(tbl_Ledger[[#This Row],[Tax Category]],Cat_Codes,0))="No",0,tbl_Ledger[[#This Row],[Amount]]*VAT_Rate) -> 206.4 | L124: =IF(INDEX(Cat_ChargesVAT,MATCH(tbl_Ledger[[#This Row],[Tax Category]],Cat_Codes,0))="No",0,tbl_Ledger[[#This Row],[Amount]]*NHIL_Rate) -> 34.4 | M124: =IF(INDEX(Cat_ChargesVAT,MATCH(tbl_Ledger[[#This Row],[Tax Category]],Cat_Codes,0))="No",0,tbl_Ledger[[#This Row],[Amount]]*GETFund_Rate) -> 34.4 | N124: =tbl_Ledger[[#This Row],[Expected VAT]]+tbl_Ledger[[#This Row],[Expected NHIL]]+tbl_Ledger[[#This Row],[Expected GETFund]] -> 275.2 | O124: =tbl_Ledger[[#This Row],[Amount]]+tbl_Ledger[[#This Row],[Tax Charged on Invoice]] -> 1651.2
B125: 118 | C125: 46113 | D125: Depot security services | E125: Greenfield IT Solutions Ltd | F125: Outflow | G125: IN_STD | H125: 5980 | I125: SIN-2026-0042 | J125: 1196 | K125: =IF(INDEX(Cat_ChargesVAT,MATCH(tbl_Ledger[[#This Row],[Tax Category]],Cat_Codes,0))="No",0,tbl_Ledger[[#This Row],[Amount]]*VAT_Rate) -> 897 | L125: =IF(INDEX(Cat_ChargesVAT,MATCH(tbl_Ledger[[#This Row],[Tax Category]],Cat_Codes,0))="No",0,tbl_Ledger[[#This Row],[Amount]]*NHIL_Rate) -> 149.5 | M125: =IF(INDEX(Cat_ChargesVAT,MATCH(tbl_Ledger[[#This Row],[Tax Category]],Cat_Codes,0))="No",0,tbl_Ledger[[#This Row],[Amount]]*GETFund_Rate) -> 149.5 | N125: =tbl_Ledger[[#This Row],[Expected VAT]]+tbl_Ledger[[#This Row],[Expected NHIL]]+tbl_Ledger[[#This Row],[Expected GETFund]] -> 1196 | O125: =tbl_Ledger[[#This Row],[Amount]]+tbl_Ledger[[#This Row],[Tax Charged on Invoice]] -> 7176
B126: 119 | C126: 46117 | D126: Cheque book and facility fees | E126: Trust Union Bank Ltd | F126: Outflow | G126: IN_EXEMPT | H126: 2138 | I126: BNK-2026-0012 | J126: 0 | K126: =IF(INDEX(Cat_ChargesVAT,MATCH(tbl_Ledger[[#This Row],[Tax Category]],Cat_Codes,0))="No",0,tbl_Ledger[[#This Row],[Amount]]*VAT_Rate) -> 0 | L126: =IF(INDEX(Cat_ChargesVAT,MATCH(tbl_Ledger[[#This Row],[Tax Category]],Cat_Codes,0))="No",0,tbl_Ledger[[#This Row],[Amount]]*NHIL_Rate) -> 0 | M126: =IF(INDEX(Cat_ChargesVAT,MATCH(tbl_Ledger[[#This Row],[Tax Category]],Cat_Codes,0))="No",0,tbl_Ledger[[#This Row],[Amount]]*GETFund_Rate) -> 0 | N126: =tbl_Ledger[[#This Row],[Expected VAT]]+tbl_Ledger[[#This Row],[Expected NHIL]]+tbl_Ledger[[#This Row],[Expected GETFund]] -> 0 | O126: =tbl_Ledger[[#This Row],[Amount]]+tbl_Ledger[[#This Row],[Tax Charged on Invoice]] -> 2138
B127: 120 | C127: 46117 | D127: Client entertainment - business development | E127: Sunset Lounge Ltd | F127: Outflow | G127: IN_NONDED | H127: 7230 | I127: SIN-2026-0043 | J127: 1446 | K127: =IF(INDEX(Cat_ChargesVAT,MATCH(tbl_Ledger[[#This Row],[Tax Category]],Cat_Codes,0))="No",0,tbl_Ledger[[#This Row],[Amount]]*VAT_Rate) -> 1084.5 | L127: =IF(INDEX(Cat_ChargesVAT,MATCH(tbl_Ledger[[#This Row],[Tax Category]],Cat_Codes,0))="No",0,tbl_Ledger[[#This Row],[Amount]]*NHIL_Rate) -> 180.75 | M127: =IF(INDEX(Cat_ChargesVAT,MATCH(tbl_Ledger[[#This Row],[Tax Category]],Cat_Codes,0))="No",0,tbl_Ledger[[#This Row],[Amount]]*GETFund_Rate) -> 180.75 | N127: =tbl_Ledger[[#This Row],[Expected VAT]]+tbl_Ledger[[#This Row],[Expected NHIL]]+tbl_Ledger[[#This Row],[Expected GETFund]] -> 1446 | O127: =tbl_Ledger[[#This Row],[Amount]]+tbl_Ledger[[#This Row],[Tax Charged on Invoice]] -> 8676
B128: 121 | C128: 46120 | D128: Contract haulage of ATK, Tema-Kumasi; customer withheld income tax at 7.5% on the service fee | E128: Northern Star BDC Ltd | F128: Inflow | G128: WHT_SVC | H128: 40648 | I128: NHL-2026-0052 | J128: 8129.6 | K128: =IF(INDEX(Cat_ChargesVAT,MATCH(tbl_Ledger[[#This Row],[Tax Category]],Cat_Codes,0))="No",0,tbl_Ledger[[#This Row],[Amount]]*VAT_Rate) -> 6097.2 | L128: =IF(INDEX(Cat_ChargesVAT,MATCH(tbl_Ledger[[#This Row],[Tax Category]],Cat_Codes,0))="No",0,tbl_Ledger[[#This Row],[Amount]]*NHIL_Rate) -> 1016.2 | M128: =IF(INDEX(Cat_ChargesVAT,MATCH(tbl_Ledger[[#This Row],[Tax Category]],Cat_Codes,0))="No",0,tbl_Ledger[[#This Row],[Amount]]*GETFund_Rate) -> 1016.2 | N128: =tbl_Ledger[[#This Row],[Expected VAT]]+tbl_Ledger[[#This Row],[Expected NHIL]]+tbl_Ledger[[#This Row],[Expected GETFund]] -> 8129.6 | O128: =tbl_Ledger[[#This Row],[Amount]]+tbl_Ledger[[#This Row],[Tax Charged on Invoice]] -> 48777.6
B129: 122 | C129: 46123 | D129: PAYE and SSNIT contributions - April | E129: Ghana Revenue Authority | F129: Outflow | G129: NO_VAT | H129: 25825 | I129: GRA-2026-0007 | J129: 0 | K129: =IF(INDEX(Cat_ChargesVAT,MATCH(tbl_Ledger[[#This Row],[Tax Category]],Cat_Codes,0))="No",0,tbl_Ledger[[#This Row],[Amount]]*VAT_Rate) -> 0 | L129: =IF(INDEX(Cat_ChargesVAT,MATCH(tbl_Ledger[[#This Row],[Tax Category]],Cat_Codes,0))="No",0,tbl_Ledger[[#This Row],[Amount]]*NHIL_Rate) -> 0 | M129: =IF(INDEX(Cat_ChargesVAT,MATCH(tbl_Ledger[[#This Row],[Tax Category]],Cat_Codes,0))="No",0,tbl_Ledger[[#This Row],[Amount]]*GETFund_Rate) -> 0 | N129: =tbl_Ledger[[#This Row],[Expected VAT]]+tbl_Ledger[[#This Row],[Expected NHIL]]+tbl_Ledger[[#This Row],[Expected GETFund]] -> 0 | O129: =tbl_Ledger[[#This Row],[Amount]]+tbl_Ledger[[#This Row],[Tax Charged on Invoice]] -> 25825
B130: 123 | C130: 46124 | D130: Bank charges and account maintenance | E130: Trust Union Bank Ltd | F130: Outflow | G130: IN_EXEMPT | H130: 1971 | I130: BNK-2026-0013 | J130: 0 | K130: =IF(INDEX(Cat_ChargesVAT,MATCH(tbl_Ledger[[#This Row],[Tax Category]],Cat_Codes,0))="No",0,tbl_Ledger[[#This Row],[Amount]]*VAT_Rate) -> 0 | L130: =IF(INDEX(Cat_ChargesVAT,MATCH(tbl_Ledger[[#This Row],[Tax Category]],Cat_Codes,0))="No",0,tbl_Ledger[[#This Row],[Amount]]*NHIL_Rate) -> 0 | M130: =IF(INDEX(Cat_ChargesVAT,MATCH(tbl_Ledger[[#This Row],[Tax Category]],Cat_Codes,0))="No",0,tbl_Ledger[[#This Row],[Amount]]*GETFund_Rate) -> 0 | N130: =tbl_Ledger[[#This Row],[Expected VAT]]+tbl_Ledger[[#This Row],[Expected NHIL]]+tbl_Ledger[[#This Row],[Expected GETFund]] -> 0 | O130: =tbl_Ledger[[#This Row],[Amount]]+tbl_Ledger[[#This Row],[Tax Charged on Invoice]] -> 1971
B131: 124 | C131: 46124 | D131: Diesel (AGO) purchased for own fleet use, 8,631 litres | E131: Zenith Fuel Depot Ltd | F131: Outflow | G131: IN_EXEMPT | H131: 81106 | I131: SIN-2026-0044 | J131: 0 | K131: =IF(INDEX(Cat_ChargesVAT,MATCH(tbl_Ledger[[#This Row],[Tax Category]],Cat_Codes,0))="No",0,tbl_Ledger[[#This Row],[Amount]]*VAT_Rate) -> 0 | L131: =IF(INDEX(Cat_ChargesVAT,MATCH(tbl_Ledger[[#This Row],[Tax Category]],Cat_Codes,0))="No",0,tbl_Ledger[[#This Row],[Amount]]*NHIL_Rate) -> 0 | M131: =IF(INDEX(Cat_ChargesVAT,MATCH(tbl_Ledger[[#This Row],[Tax Category]],Cat_Codes,0))="No",0,tbl_Ledger[[#This Row],[Amount]]*GETFund_Rate) -> 0 | N131: =tbl_Ledger[[#This Row],[Expected VAT]]+tbl_Ledger[[#This Row],[Expected NHIL]]+tbl_Ledger[[#This Row],[Expected GETFund]] -> 0 | O131: =tbl_Ledger[[#This Row],[Amount]]+tbl_Ledger[[#This Row],[Tax Charged on Invoice]] -> 81106
B132: 125 | C132: 46125 | D132: Replacement tyres for prime movers | E132: Greenfield IT Solutions Ltd | F132: Outflow | G132: IN_STD | H132: 8889 | I132: SIN-2026-0045 | J132: 1777.8 | K132: =IF(INDEX(Cat_ChargesVAT,MATCH(tbl_Ledger[[#This Row],[Tax Category]],Cat_Codes,0))="No",0,tbl_Ledger[[#This Row],[Amount]]*VAT_Rate) -> 1333.35 | L132: =IF(INDEX(Cat_ChargesVAT,MATCH(tbl_Ledger[[#This Row],[Tax Category]],Cat_Codes,0))="No",0,tbl_Ledger[[#This Row],[Amount]]*NHIL_Rate) -> 222.225 | M132: =IF(INDEX(Cat_ChargesVAT,MATCH(tbl_Ledger[[#This Row],[Tax Category]],Cat_Codes,0))="No",0,tbl_Ledger[[#This Row],[Amount]]*GETFund_Rate) -> 222.225 | N132: =tbl_Ledger[[#This Row],[Expected VAT]]+tbl_Ledger[[#This Row],[Expected NHIL]]+tbl_Ledger[[#This Row],[Expected GETFund]] -> 1777.8 | O132: =tbl_Ledger[[#This Row],[Amount]]+tbl_Ledger[[#This Row],[Tax Charged on Invoice]] -> 10666.8
B133: 126 | C133: 46125 | D133: Withholding tax remitted to GRA | E133: Meridian Bank Ghana Ltd | F133: Outflow | G133: NO_VAT | H133: 22607 | I133: JNL-2026-0003 | J133: 0 | K133: =IF(INDEX(Cat_ChargesVAT,MATCH(tbl_Ledger[[#This Row],[Tax Category]],Cat_Codes,0))="No",0,tbl_Ledger[[#This Row],[Amount]]*VAT_Rate) -> 0 | L133: =IF(INDEX(Cat_ChargesVAT,MATCH(tbl_Ledger[[#This Row],[Tax Category]],Cat_Codes,0))="No",0,tbl_Ledger[[#This Row],[Amount]]*NHIL_Rate) -> 0 | M133: =IF(INDEX(Cat_ChargesVAT,MATCH(tbl_Ledger[[#This Row],[Tax Category]],Cat_Codes,0))="No",0,tbl_Ledger[[#This Row],[Amount]]*GETFund_Rate) -> 0 | N133: =tbl_Ledger[[#This Row],[Expected VAT]]+tbl_Ledger[[#This Row],[Expected NHIL]]+tbl_Ledger[[#This Row],[Expected GETFund]] -> 0 | O133: =tbl_Ledger[[#This Row],[Amount]]+tbl_Ledger[[#This Row],[Tax Charged on Invoice]] -> 22607
... B258: 251 | C258: 46224 | D258: VAT and levies remitted to GRA for July period | E258: Ghana Revenue Authority | F258: Outflow | G258: NO_VAT | H258: 43337 | I258: GRA-2026-0014 | J258: 0 | K258: =IF(INDEX(Cat_ChargesVAT,MATCH(tbl_Ledger[[#This Row],[Tax Category]],Cat_Codes,0))="No",0,tbl_Ledger[[#This Row],[Amount]]*VAT_Rate) -> 0 | L258: =IF(INDEX(Cat_ChargesVAT,MATCH(tbl_Ledger[[#This Row],[Tax Category]],Cat_Codes,0))="No",0,tbl_Ledger[[#This Row],[Amount]]*NHIL_Rate) -> 0 | M258: =IF(INDEX(Cat_ChargesVAT,MATCH(tbl_Ledger[[#This Row],[Tax Category]],Cat_Codes,0))="No",0,tbl_Ledger[[#This Row],[Amount]]*GETFund_Rate) -> 0 | N258: =tbl_Ledger[[#This Row],[Expected VAT]]+tbl_Ledger[[#This Row],[Expected NHIL]]+tbl_Ledger[[#This Row],[Expected GETFund]] -> 0 | O258: =tbl_Ledger[[#This Row],[Amount]]+tbl_Ledger[[#This Row],[Tax Charged on Invoice]] -> 43337
B259: 252 | C259: 46228 | D259: Cheque book and facility fees | E259: Trust Union Bank Ltd | F259: Outflow | G259: IN_EXEMPT | H259: 498 | J259: 0 | K259: =IF(INDEX(Cat_ChargesVAT,MATCH(tbl_Ledger[[#This Row],[Tax Category]],Cat_Codes,0))="No",0,tbl_Ledger[[#This Row],[Amount]]*VAT_Rate) -> 0 | L259: =IF(INDEX(Cat_ChargesVAT,MATCH(tbl_Ledger[[#This Row],[Tax Category]],Cat_Codes,0))="No",0,tbl_Ledger[[#This Row],[Amount]]*NHIL_Rate) -> 0 | M259: =IF(INDEX(Cat_ChargesVAT,MATCH(tbl_Ledger[[#This Row],[Tax Category]],Cat_Codes,0))="No",0,tbl_Ledger[[#This Row],[Amount]]*GETFund_Rate) -> 0 | N259: =tbl_Ledger[[#This Row],[Expected VAT]]+tbl_Ledger[[#This Row],[Expected NHIL]]+tbl_Ledger[[#This Row],[Expected GETFund]] -> 0 | O259: =tbl_Ledger[[#This Row],[Amount]]+tbl_Ledger[[#This Row],[Tax Charged on Invoice]] -> 498
B260: 253 | C260: 46228 | D260: Bulk haulage of ATK, Tema-Kumasi, 5 trips | E260: Sankofa Petroleum Depot Ltd | F260: Inflow | G260: OUT_STD | H260: 28838 | I260: NHL-2026-0095 | J260: 5767.6 | K260: =IF(INDEX(Cat_ChargesVAT,MATCH(tbl_Ledger[[#This Row],[Tax Category]],Cat_Codes,0))="No",0,tbl_Ledger[[#This Row],[Amount]]*VAT_Rate) -> 4325.7 | L260: =IF(INDEX(Cat_ChargesVAT,MATCH(tbl_Ledger[[#This Row],[Tax Category]],Cat_Codes,0))="No",0,tbl_Ledger[[#This Row],[Amount]]*NHIL_Rate) -> 720.95 | M260: =IF(INDEX(Cat_ChargesVAT,MATCH(tbl_Ledger[[#This Row],[Tax Category]],Cat_Codes,0))="No",0,tbl_Ledger[[#This Row],[Amount]]*GETFund_Rate) -> 720.95 | N260: =tbl_Ledger[[#This Row],[Expected VAT]]+tbl_Ledger[[#This Row],[Expected NHIL]]+tbl_Ledger[[#This Row],[Expected GETFund]] -> 5767.6 | O260: =tbl_Ledger[[#This Row],[Amount]]+tbl_Ledger[[#This Row],[Tax Charged on Invoice]] -> 34605.6
B261: 254 | C261: 46229 | D261: Year-end staff function | E261: Executive Motors Ltd | F261: Outflow | G261: IN_NONDED | H261: 11715 | I261: SIN-2026-0104 | J261: 2343 | K261: =IF(INDEX(Cat_ChargesVAT,MATCH(tbl_Ledger[[#This Row],[Tax Category]],Cat_Codes,0))="No",0,tbl_Ledger[[#This Row],[Amount]]*VAT_Rate) -> 1757.25 | L261: =IF(INDEX(Cat_ChargesVAT,MATCH(tbl_Ledger[[#This Row],[Tax Category]],Cat_Codes,0))="No",0,tbl_Ledger[[#This Row],[Amount]]*NHIL_Rate) -> 292.875 | M261: =IF(INDEX(Cat_ChargesVAT,MATCH(tbl_Ledger[[#This Row],[Tax Category]],Cat_Codes,0))="No",0,tbl_Ledger[[#This Row],[Amount]]*GETFund_Rate) -> 292.875 | N261: =tbl_Ledger[[#This Row],[Expected VAT]]+tbl_Ledger[[#This Row],[Expected NHIL]]+tbl_Ledger[[#This Row],[Expected GETFund]] -> 2343 | O261: =tbl_Ledger[[#This Row],[Amount]]+tbl_Ledger[[#This Row],[Tax Charged on Invoice]] -> 14058
B262: 255 | C262: 46230 | D262: Diesel (AGO) purchased for own fleet use, 18,492 litres | E262: Zenith Fuel Depot Ltd | F262: Outflow | G262: IN_EXEMPT | H262: 53165 | I262: SIN-2026-0105 | J262: 0 | K262: =IF(INDEX(Cat_ChargesVAT,MATCH(tbl_Ledger[[#This Row],[Tax Category]],Cat_Codes,0))="No",0,tbl_Ledger[[#This Row],[Amount]]*VAT_Rate) -> 0 | L262: =IF(INDEX(Cat_ChargesVAT,MATCH(tbl_Ledger[[#This Row],[Tax Category]],Cat_Codes,0))="No",0,tbl_Ledger[[#This Row],[Amount]]*NHIL_Rate) -> 0 | M262: =IF(INDEX(Cat_ChargesVAT,MATCH(tbl_Ledger[[#This Row],[Tax Category]],Cat_Codes,0))="No",0,tbl_Ledger[[#This Row],[Amount]]*GETFund_Rate) -> 0 | N262: =tbl_Ledger[[#This Row],[Expected VAT]]+tbl_Ledger[[#This Row],[Expected NHIL]]+tbl_Ledger[[#This Row],[Expected GETFund]] -> 0 | O262: =tbl_Ledger[[#This Row],[Amount]]+tbl_Ledger[[#This Row],[Tax Charged on Invoice]] -> 53165
B263: 256 | C263: 46231 | D263: Office stationery and printing | E263: Ashanti Truck Parts Ltd | F263: Outflow | G263: IN_STD | H263: 1755 | I263: SIN-2026-0106 | J263: 351 | K263: =IF(INDEX(Cat_ChargesVAT,MATCH(tbl_Ledger[[#This Row],[Tax Category]],Cat_Codes,0))="No",0,tbl_Ledger[[#This Row],[Amount]]*VAT_Rate) -> 263.25 | L263: =IF(INDEX(Cat_ChargesVAT,MATCH(tbl_Ledger[[#This Row],[Tax Category]],Cat_Codes,0))="No",0,tbl_Ledger[[#This Row],[Amount]]*NHIL_Rate) -> 43.875 | M263: =IF(INDEX(Cat_ChargesVAT,MATCH(tbl_Ledger[[#This Row],[Tax Category]],Cat_Codes,0))="No",0,tbl_Ledger[[#This Row],[Amount]]*GETFund_Rate) -> 43.875 | N263: =tbl_Ledger[[#This Row],[Expected VAT]]+tbl_Ledger[[#This Row],[Expected NHIL]]+tbl_Ledger[[#This Row],[Expected GETFund]] -> 351 | O263: =tbl_Ledger[[#This Row],[Amount]]+tbl_Ledger[[#This Row],[Tax Charged on Invoice]] -> 2106
B264: 257 | C264: 46232 | D264: Client entertainment - business development | E264: Executive Motors Ltd | F264: Outflow | G264: IN_NONDED | H264: 11206 | I264: SIN-2026-0107 | J264: 2241.2 | K264: =IF(INDEX(Cat_ChargesVAT,MATCH(tbl_Ledger[[#This Row],[Tax Category]],Cat_Codes,0))="No",0,tbl_Ledger[[#This Row],[Amount]]*VAT_Rate) -> 1680.9 | L264: =IF(INDEX(Cat_ChargesVAT,MATCH(tbl_Ledger[[#This Row],[Tax Category]],Cat_Codes,0))="No",0,tbl_Ledger[[#This Row],[Amount]]*NHIL_Rate) -> 280.15 | M264: =IF(INDEX(Cat_ChargesVAT,MATCH(tbl_Ledger[[#This Row],[Tax Category]],Cat_Codes,0))="No",0,tbl_Ledger[[#This Row],[Amount]]*GETFund_Rate) -> 280.15 | N264: =tbl_Ledger[[#This Row],[Expected VAT]]+tbl_Ledger[[#This Row],[Expected NHIL]]+tbl_Ledger[[#This Row],[Expected GETFund]] -> 2241.2 | O264: =tbl_Ledger[[#This Row],[Amount]]+tbl_Ledger[[#This Row],[Tax Charged on Invoice]] -> 13447.2
B265: 258 | C265: 46233 | D265: Cheque book and facility fees | E265: Trust Union Bank Ltd | F265: Outflow | G265: IN_EXEMPT | H265: 558 | I265: BNK-2026-0020 | J265: 0 | K265: =IF(INDEX(Cat_ChargesVAT,MATCH(tbl_Ledger[[#This Row],[Tax Category]],Cat_Codes,0))="No",0,tbl_Ledger[[#This Row],[Amount]]*VAT_Rate) -> 0 | L265: =IF(INDEX(Cat_ChargesVAT,MATCH(tbl_Ledger[[#This Row],[Tax Category]],Cat_Codes,0))="No",0,tbl_Ledger[[#This Row],[Amount]]*NHIL_Rate) -> 0 | M265: =IF(INDEX(Cat_ChargesVAT,MATCH(tbl_Ledger[[#This Row],[Tax Category]],Cat_Codes,0))="No",0,tbl_Ledger[[#This Row],[Amount]]*GETFund_Rate) -> 0 | N265: =tbl_Ledger[[#This Row],[Expected VAT]]+tbl_Ledger[[#This Row],[Expected NHIL]]+tbl_Ledger[[#This Row],[Expected GETFund]] -> 0 | O265: =tbl_Ledger[[#This Row],[Amount]]+tbl_Ledger[[#This Row],[Tax Charged on Invoice]] -> 558
B266: 259 | C266: 46233 | D266: Term haulage contract, ATK, Tema-Takoradi; customer is an appointed VAT withholding agent and retained 7% | E266: Northern Star BDC Ltd | F266: Inflow | G266: VAT_WHT | H266: 161339 | I266: NHL-2026-0096 | J266: 32267.8 | K266: =IF(INDEX(Cat_ChargesVAT,MATCH(tbl_Ledger[[#This Row],[Tax Category]],Cat_Codes,0))="No",0,tbl_Ledger[[#This Row],[Amount]]*VAT_Rate) -> 24200.85 | L266: =IF(INDEX(Cat_ChargesVAT,MATCH(tbl_Ledger[[#This Row],[Tax Category]],Cat_Codes,0))="No",0,tbl_Ledger[[#This Row],[Amount]]*NHIL_Rate) -> 4033.475 | M266: =IF(INDEX(Cat_ChargesVAT,MATCH(tbl_Ledger[[#This Row],[Tax Category]],Cat_Codes,0))="No",0,tbl_Ledger[[#This Row],[Amount]]*GETFund_Rate) -> 4033.475 | N266: =tbl_Ledger[[#This Row],[Expected VAT]]+tbl_Ledger[[#This Row],[Expected NHIL]]+tbl_Ledger[[#This Row],[Expected GETFund]] -> 32267.8 | O266: =tbl_Ledger[[#This Row],[Amount]]+tbl_Ledger[[#This Row],[Tax Charged on Invoice]] -> 193606.8
B267: 260 | C267: 46234 | D267: Staff salaries and wages - July | E267: Nkabom Haulage Payroll | F267: Outflow | G267: NO_VAT | H267: 118377 | I267: PAY-2026-0007 | J267: 0 | K267: =IF(INDEX(Cat_ChargesVAT,MATCH(tbl_Ledger[[#This Row],[Tax Category]],Cat_Codes,0))="No",0,tbl_Ledger[[#This Row],[Amount]]*VAT_Rate) -> 0 | L267: =IF(INDEX(Cat_ChargesVAT,MATCH(tbl_Ledger[[#This Row],[Tax Category]],Cat_Codes,0))="No",0,tbl_Ledger[[#This Row],[Amount]]*NHIL_Rate) -> 0 | M267: =IF(INDEX(Cat_ChargesVAT,MATCH(tbl_Ledger[[#This Row],[Tax Category]],Cat_Codes,0))="No",0,tbl_Ledger[[#This Row],[Amount]]*GETFund_Rate) -> 0 | N267: =tbl_Ledger[[#This Row],[Expected VAT]]+tbl_Ledger[[#This Row],[Expected NHIL]]+tbl_Ledger[[#This Row],[Expected GETFund]] -> 0 | O267: =tbl_Ledger[[#This Row],[Amount]]+tbl_Ledger[[#This Row],[Tax Charged on Invoice]] -> 118377
B268: 261 | C268: 46235 | D268: Third-party liability cover premium | E268: Unity Assurance Ltd | F268: Outflow | G268: IN_EXEMPT | H268: 15411 | I268: SIN-2026-0108 | J268: 0 | K268: =IF(INDEX(Cat_ChargesVAT,MATCH(tbl_Ledger[[#This Row],[Tax Category]],Cat_Codes,0))="No",0,tbl_Ledger[[#This Row],[Amount]]*VAT_Rate) -> 0 | L268: =IF(INDEX(Cat_ChargesVAT,MATCH(tbl_Ledger[[#This Row],[Tax Category]],Cat_Codes,0))="No",0,tbl_Ledger[[#This Row],[Amount]]*NHIL_Rate) -> 0 | M268: =IF(INDEX(Cat_ChargesVAT,MATCH(tbl_Ledger[[#This Row],[Tax Category]],Cat_Codes,0))="No",0,tbl_Ledger[[#This Row],[Amount]]*GETFund_Rate) -> 0 | N268: =tbl_Ledger[[#This Row],[Expected VAT]]+tbl_Ledger[[#This Row],[Expected NHIL]]+tbl_Ledger[[#This Row],[Expected GETFund]] -> 0 | O268: =tbl_Ledger[[#This Row],[Amount]]+tbl_Ledger[[#This Row],[Tax Charged on Invoice]] -> 15411
B269: 262 | C269: 46235 | D269: Passenger vehicle running costs - management car | E269: Labadi Grill House Ltd | F269: Outflow | G269: IN_NONDED | H269: 2821 | I269: SIN-2026-0109 | J269: 564.2 | K269: =IF(INDEX(Cat_ChargesVAT,MATCH(tbl_Ledger[[#This Row],[Tax Category]],Cat_Codes,0))="No",0,tbl_Ledger[[#This Row],[Amount]]*VAT_Rate) -> 423.15 | L269: =IF(INDEX(Cat_ChargesVAT,MATCH(tbl_Ledger[[#This Row],[Tax Category]],Cat_Codes,0))="No",0,tbl_Ledger[[#This Row],[Amount]]*NHIL_Rate) -> 70.525 | M269: =IF(INDEX(Cat_ChargesVAT,MATCH(tbl_Ledger[[#This Row],[Tax Category]],Cat_Codes,0))="No",0,tbl_Ledger[[#This Row],[Amount]]*GETFund_Rate) -> 70.525 | N269: =tbl_Ledger[[#This Row],[Expected VAT]]+tbl_Ledger[[#This Row],[Expected NHIL]]+tbl_Ledger[[#This Row],[Expected GETFund]] -> 564.2 | O269: =tbl_Ledger[[#This Row],[Amount]]+tbl_Ledger[[#This Row],[Tax Charged on Invoice]] -> 3385.2
B270: 263 | C270: 46235 | D270: Term haulage contract, ATK, Takoradi-Tamale; customer is an appointed VAT withholding agent and retained 7% | E270: Northern Star BDC Ltd | F270: Inflow | G270: VAT_WHT | H270: 109604 | I270: NHL-2026-0097 | J270: 21920.8 | K270: =IF(INDEX(Cat_ChargesVAT,MATCH(tbl_Ledger[[#This Row],[Tax Category]],Cat_Codes,0))="No",0,tbl_Ledger[[#This Row],[Amount]]*VAT_Rate) -> 16440.6 | L270: =IF(INDEX(Cat_ChargesVAT,MATCH(tbl_Ledger[[#This Row],[Tax Category]],Cat_Codes,0))="No",0,tbl_Ledger[[#This Row],[Amount]]*NHIL_Rate) -> 2740.1 | M270: =IF(INDEX(Cat_ChargesVAT,MATCH(tbl_Ledger[[#This Row],[Tax Category]],Cat_Codes,0))="No",0,tbl_Ledger[[#This Row],[Amount]]*GETFund_Rate) -> 2740.1 | N270: =tbl_Ledger[[#This Row],[Expected VAT]]+tbl_Ledger[[#This Row],[Expected NHIL]]+tbl_Ledger[[#This Row],[Expected GETFund]] -> 21920.8 | O270: =tbl_Ledger[[#This Row],[Amount]]+tbl_Ledger[[#This Row],[Tax Charged on Invoice]] -> 131524.8
B271: 264 | C271: 46236 | D271: Transfer and settlement charges | E271: Trust Union Bank Ltd | F271: Outflow | G271: IN_EXEMPT | H271: 3299 | I271: BNK-2026-0021 | J271: 0 | K271: =IF(INDEX(Cat_ChargesVAT,MATCH(tbl_Ledger[[#This Row],[Tax Category]],Cat_Codes,0))="No",0,tbl_Ledger[[#This Row],[Amount]]*VAT_Rate) -> 0 | L271: =IF(INDEX(Cat_ChargesVAT,MATCH(tbl_Ledger[[#This Row],[Tax Category]],Cat_Codes,0))="No",0,tbl_Ledger[[#This Row],[Amount]]*NHIL_Rate) -> 0 | M271: =IF(INDEX(Cat_ChargesVAT,MATCH(tbl_Ledger[[#This Row],[Tax Category]],Cat_Codes,0))="No",0,tbl_Ledger[[#This Row],[Amount]]*GETFund_Rate) -> 0 | N271: =tbl_Ledger[[#This Row],[Expected VAT]]+tbl_Ledger[[#This Row],[Expected NHIL]]+tbl_Ledger[[#This Row],[Expected GETFund]] -> 0 | O271: =tbl_Ledger[[#This Row],[Amount]]+tbl_Ledger[[#This Row],[Tax Charged on Invoice]] -> 3299
... B307: 300 | C307: 46265 | D307: Bulk haulage of LPG, Tema-Ho, 3 trips | E307: Golden Harmattan Energy Ltd | F307: Inflow | G307: OUT_STD | H307: 33337 | I307: NHL-2026-0113 | J307: 6667.4 | K307: =IF(INDEX(Cat_ChargesVAT,MATCH(tbl_Ledger[[#This Row],[Tax Category]],Cat_Codes,0))="No",0,tbl_Ledger[[#This Row],[Amount]]*VAT_Rate) -> 5000.55 | L307: =IF(INDEX(Cat_ChargesVAT,MATCH(tbl_Ledger[[#This Row],[Tax Category]],Cat_Codes,0))="No",0,tbl_Ledger[[#This Row],[Amount]]*NHIL_Rate) -> 833.425 | M307: =IF(INDEX(Cat_ChargesVAT,MATCH(tbl_Ledger[[#This Row],[Tax Category]],Cat_Codes,0))="No",0,tbl_Ledger[[#This Row],[Amount]]*GETFund_Rate) -> 833.425 | N307: =tbl_Ledger[[#This Row],[Expected VAT]]+tbl_Ledger[[#This Row],[Expected NHIL]]+tbl_Ledger[[#This Row],[Expected GETFund]] -> 6667.4 | O307: =tbl_Ledger[[#This Row],[Amount]]+tbl_Ledger[[#This Row],[Tax Charged on Invoice]] -> 40004.4

Sheet VAT_Recon
B1: NKABOM HAULAGE LTD — CORE TAX ENGINE
B2: Sheet 4 of 6 • Monthly VAT & Levy Reconciliation • Simulation period January to August 2026
B3: SIMULATION ONLY — figures are fictitious. Every amount below is a formula reading the Ledger; nothing on this sheet is typed. Not a filed return and not tax advice.
B5: A. MONTHLY VAT AND LEVY RECONCILIATION
C6: OUTPUT TAX — charged on supplies made | F6: INPUT TAX — incurred on supplies received
B7: Month | C7: Output VAT | D7: Output NHIL | E7: Output GETFund | F7: Input VAT | G7: Input NHIL | H7: Input GETFund | I7: Net VAT Payable / (Recoverable) | J7: Sense check
B8: Ledger Direction filter applied → | C8: Inflow | D8: Inflow | E8: Inflow | F8: Outflow | G8: Outflow | H8: Outflow
B9: =DATE(Ledger_Year,1,1) -> 46023 | C9: {=SUMPRODUCT((YEAR(Ledger!$C$8:$C$307)=YEAR($B9))*(MONTH(Ledger!$C$8:$C$307)=MONTH($B9))*(Ledger!$F$8:$F$307=C$8)*(INDEX(Cat_ChargesVAT,MATCH(Ledger!$G$8:$G$307,Cat_Codes,0))="Yes")*Ledger!$K$8:$K$307)} -> 195161.4 | D9: {=SUMPRODUCT((YEAR(Ledger!$C$8:$C$307)=YEAR($B9))*(MONTH(Ledger!$C$8:$C$307)=MONTH($B9))*(Ledger!$F$8:$F$307=D$8)*(INDEX(Cat_ChargesVAT,MATCH(Ledger!$G$8:$G$307,Cat_Codes,0))="Yes")*Ledger!$L$8:$L$307)} -> 32526.9 | E9: {=SUMPRODUCT((YEAR(Ledger!$C$8:$C$307)=YEAR($B9))*(MONTH(Ledger!$C$8:$C$307)=MONTH($B9))*(Ledger!$F$8:$F$307=E$8)*(INDEX(Cat_ChargesVAT,MATCH(Ledger!$G$8:$G$307,Cat_Codes,0))="Yes")*Ledger!$M$8:$M$307)} -> 32526.9 | F9: {=SUMPRODUCT((YEAR(Ledger!$C$8:$C$307)=YEAR($B9))*(MONTH(Ledger!$C$8:$C$307)=MONTH($B9))*(Ledger!$F$8:$F$307=F$8)*(INDEX(Cat_Recoverable,MATCH(Ledger!$G$8:$G$307,Cat_Codes,0))="Yes")*Ledger!$K$8:$K$307)} -> 14008.95 | G9: {=SUMPRODUCT((YEAR(Ledger!$C$8:$C$307)=YEAR($B9))*(MONTH(Ledger!$C$8:$C$307)=MONTH($B9))*(Ledger!$F$8:$F$307=G$8)*(INDEX(Cat_Recoverable,MATCH(Ledger!$G$8:$G$307,Cat_Codes,0))="Yes")*Ledger!$L$8:$L$307)} -> 2334.825 | H9: {=SUMPRODUCT((YEAR(Ledger!$C$8:$C$307)=YEAR($B9))*(MONTH(Ledger!$C$8:$C$307)=MONTH($B9))*(Ledger!$F$8:$F$307=H$8)*(INDEX(Cat_Recoverable,MATCH(Ledger!$G$8:$G$307,Cat_Codes,0))="Yes")*Ledger!$M$8:$M$307)} -> 2334.825 | I9: =(C9+D9+E9)-(F9+G9+H9) -> 241536.6 | J9: =IF(I9<0,"Net credit — review","Net payable") -> Net payable
B10: =EDATE(B9,1) -> 46054 | C10: {=SUMPRODUCT((YEAR(Ledger!$C$8:$C$307)=YEAR($B10))*(MONTH(Ledger!$C$8:$C$307)=MONTH($B10))*(Ledger!$F$8:$F$307=C$8)*(INDEX(Cat_ChargesVAT,MATCH(Ledger!$G$8:$G$307,Cat_Codes,0))="Yes")*Ledger!$K$8:$K$307)} -> 134963.85 | D10: {=SUMPRODUCT((YEAR(Ledger!$C$8:$C$307)=YEAR($B10))*(MONTH(Ledger!$C$8:$C$307)=MONTH($B10))*(Ledger!$F$8:$F$307=D$8)*(INDEX(Cat_ChargesVAT,MATCH(Ledger!$G$8:$G$307,Cat_Codes,0))="Yes")*Ledger!$L$8:$L$307)} -> 22493.975 | E10: {=SUMPRODUCT((YEAR(Ledger!$C$8:$C$307)=YEAR($B10))*(MONTH(Ledger!$C$8:$C$307)=MONTH($B10))*(Ledger!$F$8:$F$307=E$8)*(INDEX(Cat_ChargesVAT,MATCH(Ledger!$G$8:$G$307,Cat_Codes,0))="Yes")*Ledger!$M$8:$M$307)} -> 22493.975 | F10: {=SUMPRODUCT((YEAR(Ledger!$C$8:$C$307)=YEAR($B10))*(MONTH(Ledger!$C$8:$C$307)=MONTH($B10))*(Ledger!$F$8:$F$307=F$8)*(INDEX(Cat_Recoverable,MATCH(Ledger!$G$8:$G$307,Cat_Codes,0))="Yes")*Ledger!$K$8:$K$307)} -> 11309.25 | G10: {=SUMPRODUCT((YEAR(Ledger!$C$8:$C$307)=YEAR($B10))*(MONTH(Ledger!$C$8:$C$307)=MONTH($B10))*(Ledger!$F$8:$F$307=G$8)*(INDEX(Cat_Recoverable,MATCH(Ledger!$G$8:$G$307,Cat_Codes,0))="Yes")*Ledger!$L$8:$L$307)} -> 1884.875 | H10: {=SUMPRODUCT((YEAR(Ledger!$C$8:$C$307)=YEAR($B10))*(MONTH(Ledger!$C$8:$C$307)=MONTH($B10))*(Ledger!$F$8:$F$307=H$8)*(INDEX(Cat_Recoverable,MATCH(Ledger!$G$8:$G$307,Cat_Codes,0))="Yes")*Ledger!$M$8:$M$307)} -> 1884.875 | I10: =(C10+D10+E10)-(F10+G10+H10) -> 164872.8 | J10: =IF(I10<0,"Net credit — review","Net payable") -> Net payable
B11: =EDATE(B10,1) -> 46082 | C11: {=SUMPRODUCT((YEAR(Ledger!$C$8:$C$307)=YEAR($B11))*(MONTH(Ledger!$C$8:$C$307)=MONTH($B11))*(Ledger!$F$8:$F$307=C$8)*(INDEX(Cat_ChargesVAT,MATCH(Ledger!$G$8:$G$307,Cat_Codes,0))="Yes")*Ledger!$K$8:$K$307)} -> 159072.9 | D11: {=SUMPRODUCT((YEAR(Ledger!$C$8:$C$307)=YEAR($B11))*(MONTH(Ledger!$C$8:$C$307)=MONTH($B11))*(Ledger!$F$8:$F$307=D$8)*(INDEX(Cat_ChargesVAT,MATCH(Ledger!$G$8:$G$307,Cat_Codes,0))="Yes")*Ledger!$L$8:$L$307)} -> 26512.15 | E11: {=SUMPRODUCT((YEAR(Ledger!$C$8:$C$307)=YEAR($B11))*(MONTH(Ledger!$C$8:$C$307)=MONTH($B11))*(Ledger!$F$8:$F$307=E$8)*(INDEX(Cat_ChargesVAT,MATCH(Ledger!$G$8:$G$307,Cat_Codes,0))="Yes")*Ledger!$M$8:$M$307)} -> 26512.15 | F11: {=SUMPRODUCT((YEAR(Ledger!$C$8:$C$307)=YEAR($B11))*(MONTH(Ledger!$C$8:$C$307)=MONTH($B11))*(Ledger!$F$8:$F$307=F$8)*(INDEX(Cat_Recoverable,MATCH(Ledger!$G$8:$G$307,Cat_Codes,0))="Yes")*Ledger!$K$8:$K$307)} -> 11403 | G11: {=SUMPRODUCT((YEAR(Ledger!$C$8:$C$307)=YEAR($B11))*(MONTH(Ledger!$C$8:$C$307)=MONTH($B11))*(Ledger!$F$8:$F$307=G$8)*(INDEX(Cat_Recoverable,MATCH(Ledger!$G$8:$G$307,Cat_Codes,0))="Yes")*Ledger!$L$8:$L$307)} -> 1900.5 | H11: {=SUMPRODUCT((YEAR(Ledger!$C$8:$C$307)=YEAR($B11))*(MONTH(Ledger!$C$8:$C$307)=MONTH($B11))*(Ledger!$F$8:$F$307=H$8)*(INDEX(Cat_Recoverable,MATCH(Ledger!$G$8:$G$307,Cat_Codes,0))="Yes")*Ledger!$M$8:$M$307)} -> 1900.5 | I11: =(C11+D11+E11)-(F11+G11+H11) -> 196893.2 | J11: =IF(I11<0,"Net credit — review","Net payable") -> Net payable
B12: =EDATE(B11,1) -> 46113 | C12: {=SUMPRODUCT((YEAR(Ledger!$C$8:$C$307)=YEAR($B12))*(MONTH(Ledger!$C$8:$C$307)=MONTH($B12))*(Ledger!$F$8:$F$307=C$8)*(INDEX(Cat_ChargesVAT,MATCH(Ledger!$G$8:$G$307,Cat_Codes,0))="Yes")*Ledger!$K$8:$K$307)} -> 112738.8 | D12: {=SUMPRODUCT((YEAR(Ledger!$C$8:$C$307)=YEAR($B12))*(MONTH(Ledger!$C$8:$C$307)=MONTH($B12))*(Ledger!$F$8:$F$307=D$8)*(INDEX(Cat_ChargesVAT,MATCH(Ledger!$G$8:$G$307,Cat_Codes,0))="Yes")*Ledger!$L$8:$L$307)} -> 18789.8 | E12: {=SUMPRODUCT((YEAR(Ledger!$C$8:$C$307)=YEAR($B12))*(MONTH(Ledger!$C$8:$C$307)=MONTH($B12))*(Ledger!$F$8:$F$307=E$8)*(INDEX(Cat_ChargesVAT,MATCH(Ledger!$G$8:$G$307,Cat_Codes,0))="Yes")*Ledger!$M$8:$M$307)} -> 18789.8 | F12: {=SUMPRODUCT((YEAR(Ledger!$C$8:$C$307)=YEAR($B12))*(MONTH(Ledger!$C$8:$C$307)=MONTH($B12))*(Ledger!$F$8:$F$307=F$8)*(INDEX(Cat_Recoverable,MATCH(Ledger!$G$8:$G$307,Cat_Codes,0))="Yes")*Ledger!$K$8:$K$307)} -> 13625.7 | G12: {=SUMPRODUCT((YEAR(Ledger!$C$8:$C$307)=YEAR($B12))*(MONTH(Ledger!$C$8:$C$307)=MONTH($B12))*(Ledger!$F$8:$F$307=G$8)*(INDEX(Cat_Recoverable,MATCH(Ledger!$G$8:$G$307,Cat_Codes,0))="Yes")*Ledger!$L$8:$L$307)} -> 2270.95 | H12: {=SUMPRODUCT((YEAR(Ledger!$C$8:$C$307)=YEAR($B12))*(MONTH(Ledger!$C$8:$C$307)=MONTH($B12))*(Ledger!$F$8:$F$307=H$8)*(INDEX(Cat_Recoverable,MATCH(Ledger!$G$8:$G$307,Cat_Codes,0))="Yes")*Ledger!$M$8:$M$307)} -> 2270.95 | I12: =(C12+D12+E12)-(F12+G12+H12) -> 132150.8 | J12: =IF(I12<0,"Net credit — review","Net payable") -> Net payable
B13: =EDATE(B12,1) -> 46143 | C13: {=SUMPRODUCT((YEAR(Ledger!$C$8:$C$307)=YEAR($B13))*(MONTH(Ledger!$C$8:$C$307)=MONTH($B13))*(Ledger!$F$8:$F$307=C$8)*(INDEX(Cat_ChargesVAT,MATCH(Ledger!$G$8:$G$307,Cat_Codes,0))="Yes")*Ledger!$K$8:$K$307)} -> 111840.3 | D13: {=SUMPRODUCT((YEAR(Ledger!$C$8:$C$307)=YEAR($B13))*(MONTH(Ledger!$C$8:$C$307)=MONTH($B13))*(Ledger!$F$8:$F$307=D$8)*(INDEX(Cat_ChargesVAT,MATCH(Ledger!$G$8:$G$307,Cat_Codes,0))="Yes")*Ledger!$L$8:$L$307)} -> 18640.05 | E13: {=SUMPRODUCT((YEAR(Ledger!$C$8:$C$307)=YEAR($B13))*(MONTH(Ledger!$C$8:$C$307)=MONTH($B13))*(Ledger!$F$8:$F$307=E$8)*(INDEX(Cat_ChargesVAT,MATCH(Ledger!$G$8:$G$307,Cat_Codes,0))="Yes")*Ledger!$M$8:$M$307)} -> 18640.05 | F13: {=SUMPRODUCT((YEAR(Ledger!$C$8:$C$307)=YEAR($B13))*(MONTH(Ledger!$C$8:$C$307)=MONTH($B13))*(Ledger!$F$8:$F$307=F$8)*(INDEX(Cat_Recoverable,MATCH(Ledger!$G$8:$G$307,Cat_Codes,0))="Yes")*Ledger!$K$8:$K$307)} -> 18886.05 | G13: {=SUMPRODUCT((YEAR(Ledger!$C$8:$C$307)=YEAR($B13))*(MONTH(Ledger!$C$8:$C$307)=MONTH($B13))*(Ledger!$F$8:$F$307=G$8)*(INDEX(Cat_Recoverable,MATCH(Ledger!$G$8:$G$307,Cat_Codes,0))="Yes")*Ledger!$L$8:$L$307)} -> 3147.675 | H13: {=SUMPRODUCT((YEAR(Ledger!$C$8:$C$307)=YEAR($B13))*(MONTH(Ledger!$C$8:$C$307)=MONTH($B13))*(Ledger!$F$8:$F$307=H$8)*(INDEX(Cat_Recoverable,MATCH(Ledger!$G$8:$G$307,Cat_Codes,0))="Yes")*Ledger!$M$8:$M$307)} -> 3147.675 | I13: =(C13+D13+E13)-(F13+G13+H13) -> 123939 | J13: =IF(I13<0,"Net credit — review","Net payable") -> Net payable
B14: =EDATE(B13,1) -> 46174 | C14: {=SUMPRODUCT((YEAR(Ledger!$C$8:$C$307)=YEAR($B14))*(MONTH(Ledger!$C$8:$C$307)=MONTH($B14))*(Ledger!$F$8:$F$307=C$8)*(INDEX(Cat_ChargesVAT,MATCH(Ledger!$G$8:$G$307,Cat_Codes,0))="Yes")*Ledger!$K$8:$K$307)} -> 110459.55 | D14: {=SUMPRODUCT((YEAR(Ledger!$C$8:$C$307)=YEAR($B14))*(MONTH(Ledger!$C$8:$C$307)=MONTH($B14))*(Ledger!$F$8:$F$307=D$8)*(INDEX(Cat_ChargesVAT,MATCH(Ledger!$G$8:$G$307,Cat_Codes,0))="Yes")*Ledger!$L$8:$L$307)} -> 18409.925 | E14: {=SUMPRODUCT((YEAR(Ledger!$C$8:$C$307)=YEAR($B14))*(MONTH(Ledger!$C$8:$C$307)=MONTH($B14))*(Ledger!$F$8:$F$307=E$8)*(INDEX(Cat_ChargesVAT,MATCH(Ledger!$G$8:$G$307,Cat_Codes,0))="Yes")*Ledger!$M$8:$M$307)} -> 18409.925 | F14: {=SUMPRODUCT((YEAR(Ledger!$C$8:$C$307)=YEAR($B14))*(MONTH(Ledger!$C$8:$C$307)=MONTH($B14))*(Ledger!$F$8:$F$307=F$8)*(INDEX(Cat_Recoverable,MATCH(Ledger!$G$8:$G$307,Cat_Codes,0))="Yes")*Ledger!$K$8:$K$307)} -> 13124.25 | G14: {=SUMPRODUCT((YEAR(Ledger!$C$8:$C$307)=YEAR($B14))*(MONTH(Ledger!$C$8:$C$307)=MONTH($B14))*(Ledger!$F$8:$F$307=G$8)*(INDEX(Cat_Recoverable,MATCH(Ledger!$G$8:$G$307,Cat_Codes,0))="Yes")*Ledger!$L$8:$L$307)} -> 2187.375 | H14: {=SUMPRODUCT((YEAR(Ledger!$C$8:$C$307)=YEAR($B14))*(MONTH(Ledger!$C$8:$C$307)=MONTH($B14))*(Ledger!$F$8:$F$307=H$8)*(INDEX(Cat_Recoverable,MATCH(Ledger!$G$8:$G$307,Cat_Codes,0))="Yes")*Ledger!$M$8:$M$307)} -> 2187.375 | I14: =(C14+D14+E14)-(F14+G14+H14) -> 129780.4 | J14: =IF(I14<0,"Net credit — review","Net payable") -> Net payable
B15: =EDATE(B14,1) -> 46204 | C15: {=SUMPRODUCT((YEAR(Ledger!$C$8:$C$307)=YEAR($B15))*(MONTH(Ledger!$C$8:$C$307)=MONTH($B15))*(Ledger!$F$8:$F$307=C$8)*(INDEX(Cat_ChargesVAT,MATCH(Ledger!$G$8:$G$307,Cat_Codes,0))="Yes")*Ledger!$K$8:$K$307)} -> 127974.15 | D15: {=SUMPRODUCT((YEAR(Ledger!$C$8:$C$307)=YEAR($B15))*(MONTH(Ledger!$C$8:$C$307)=MONTH($B15))*(Ledger!$F$8:$F$307=D$8)*(INDEX(Cat_ChargesVAT,MATCH(Ledger!$G$8:$G$307,Cat_Codes,0))="Yes")*Ledger!$L$8:$L$307)} -> 21329.025 | E15: {=SUMPRODUCT((YEAR(Ledger!$C$8:$C$307)=YEAR($B15))*(MONTH(Ledger!$C$8:$C$307)=MONTH($B15))*(Ledger!$F$8:$F$307=E$8)*(INDEX(Cat_ChargesVAT,MATCH(Ledger!$G$8:$G$307,Cat_Codes,0))="Yes")*Ledger!$M$8:$M$307)} -> 21329.025 | F15: {=SUMPRODUCT((YEAR(Ledger!$C$8:$C$307)=YEAR($B15))*(MONTH(Ledger!$C$8:$C$307)=MONTH($B15))*(Ledger!$F$8:$F$307=F$8)*(INDEX(Cat_Recoverable,MATCH(Ledger!$G$8:$G$307,Cat_Codes,0))="Yes")*Ledger!$K$8:$K$307)} -> 4345.95 | G15: {=SUMPRODUCT((YEAR(Ledger!$C$8:$C$307)=YEAR($B15))*(MONTH(Ledger!$C$8:$C$307)=MONTH($B15))*(Ledger!$F$8:$F$307=G$8)*(INDEX(Cat_Recoverable,MATCH(Ledger!$G$8:$G$307,Cat_Codes,0))="Yes")*Ledger!$L$8:$L$307)} -> 724.325 | H15: {=SUMPRODUCT((YEAR(Ledger!$C$8:$C$307)=YEAR($B15))*(MONTH(Ledger!$C$8:$C$307)=MONTH($B15))*(Ledger!$F$8:$F$307=H$8)*(INDEX(Cat_Recoverable,MATCH(Ledger!$G$8:$G$307,Cat_Codes,0))="Yes")*Ledger!$M$8:$M$307)} -> 724.325 | I15: =(C15+D15+E15)-(F15+G15+H15) -> 164837.6 | J15: =IF(I15<0,"Net credit — review","Net payable") -> Net payable
B16: =EDATE(B15,1) -> 46235 | C16: {=SUMPRODUCT((YEAR(Ledger!$C$8:$C$307)=YEAR($B16))*(MONTH(Ledger!$C$8:$C$307)=MONTH($B16))*(Ledger!$F$8:$F$307=C$8)*(INDEX(Cat_ChargesVAT,MATCH(Ledger!$G$8:$G$307,Cat_Codes,0))="Yes")*Ledger!$K$8:$K$307)} -> 164205.3 | D16: {=SUMPRODUCT((YEAR(Ledger!$C$8:$C$307)=YEAR($B16))*(MONTH(Ledger!$C$8:$C$307)=MONTH($B16))*(Ledger!$F$8:$F$307=D$8)*(INDEX(Cat_ChargesVAT,MATCH(Ledger!$G$8:$G$307,Cat_Codes,0))="Yes")*Ledger!$L$8:$L$307)} -> 27367.55 | E16: {=SUMPRODUCT((YEAR(Ledger!$C$8:$C$307)=YEAR($B16))*(MONTH(Ledger!$C$8:$C$307)=MONTH($B16))*(Ledger!$F$8:$F$307=E$8)*(INDEX(Cat_ChargesVAT,MATCH(Ledger!$G$8:$G$307,Cat_Codes,0))="Yes")*Ledger!$M$8:$M$307)} -> 27367.55 | F16: {=SUMPRODUCT((YEAR(Ledger!$C$8:$C$307)=YEAR($B16))*(MONTH(Ledger!$C$8:$C$307)=MONTH($B16))*(Ledger!$F$8:$F$307=F$8)*(INDEX(Cat_Recoverable,MATCH(Ledger!$G$8:$G$307,Cat_Codes,0))="Yes")*Ledger!$K$8:$K$307)} -> 11128.35 | G16: {=SUMPRODUCT((YEAR(Ledger!$C$8:$C$307)=YEAR($B16))*(MONTH(Ledger!$C$8:$C$307)=MONTH($B16))*(Ledger!$F$8:$F$307=G$8)*(INDEX(Cat_Recoverable,MATCH(Ledger!$G$8:$G$307,Cat_Codes,0))="Yes")*Ledger!$L$8:$L$307)} -> 1854.725 | H16: {=SUMPRODUCT((YEAR(Ledger!$C$8:$C$307)=YEAR($B16))*(MONTH(Ledger!$C$8:$C$307)=MONTH($B16))*(Ledger!$F$8:$F$307=H$8)*(INDEX(Cat_Recoverable,MATCH(Ledger!$G$8:$G$307,Cat_Codes,0))="Yes")*Ledger!$M$8:$M$307)} -> 1854.725 | I16: =(C16+D16+E16)-(F16+G16+H16) -> 204102.6 | J16: =IF(I16<0,"Net credit — review","Net payable") -> Net payable
B17: TOTAL Jan–Aug | C17: =SUM(C9:C16) -> 1116416.2 | D17: =SUM(D9:D16) -> 186069.37 | E17: =SUM(E9:E16) -> 186069.37 | F17: =SUM(F9:F16) -> 97831.5 | G17: =SUM(G9:G16) -> 16305.25 | H17: =SUM(H9:H16) -> 16305.25 | I17: =SUM(I9:I16) -> 1358113 | J17: =IF(I17<0,"Net credit — review","Net payable") -> Net payable
B19: B. CONTROL CHECKS — completeness and tie-out to the Ledger
B20: Control check | F20: Expected | G20: Actual | H20: Status
B21: 1. Every Ledger transaction falls inside the eight months reported above | F21: =COUNTA(Ledger!$B$8:$B$307) -> 300 | G21: {=SUMPRODUCT((Ledger!$C$8:$C$307>=$B$9)*(Ledger!$C$8:$C$307<=EOMONTH($B$16,0))*1)} -> 300 | H21: =IF(F21=G21,"OK","REVIEW") -> OK
B22: 2. Total Output VAT ties to the Ledger's Expected VAT on all money-in rows | F22: {=SUMPRODUCT((Ledger!$F$8:$F$307=$C$8)*Ledger!$K$8:$K$307)} -> 1116416.3 | G22: =C17 -> 1116416.2 | H22: =IF(ROUND(F22-G22,2)=0,"OK","REVIEW") -> OK
B23: 3. Total Input VAT ties to the Ledger's Expected VAT on money-out rows in recoverable categories | F23: {=SUMPRODUCT((Ledger!$F$8:$F$307=$F$8)*(INDEX(Cat_Recoverable,MATCH(Ledger!$G$8:$G$307,Cat_Codes,0))="Yes")*Ledger!$K$8:$K$307)} -> 97831.5 | G23: =F17 -> 97831.5 | H23: =IF(ROUND(F23-G23,2)=0,"OK","REVIEW") -> OK
B24: 4. Total expected tax per the Ledger equals output tax, plus input tax reported, plus input tax excluded as non-recoverable | F24: =SUM(Ledger!$N$8:$N$307) -> 1635833.6 | G24: =C17+D17+E17+F17+G17+H17+G27 -> 1635833.6 | H24: =IF(ROUND(F24-G24,2)=0,"OK","REVIEW") -> OK
B25: 5. Monthly Net VAT figures add back to the Total row | F25: =SUM(I9:I16) -> 1358113 | G25: =I17 -> 1358113 | H25: =IF(ROUND(F25-G25,2)=0,"OK","REVIEW") -> OK
B26: 6. Eight distinct months are reported, with no gap or repeat | F26: 8 | G26: {=SUMPRODUCT(1/COUNTIF(B9:B16,B9:B16))} -> 8 | H26: =IF(F26=G26,"OK","REVIEW") -> OK
B27: 7. Input tax excluded from columns F to H because the category is not recoverable | F27: {=SUMPRODUCT((Ledger!$F$8:$F$307=$F$8)*Ledger!$N$8:$N$307)-(F17+G17+H17)} -> 16836.6 | G27: {=SUMPRODUCT((Ledger!$F$8:$F$307=$F$8)*(INDEX(Cat_Recoverable,MATCH(Ledger!$G$8:$G$307,Cat_Codes,0))="No")*Ledger!$N$8:$N$307)} -> 16836.6 | H27: =IF(ROUND(F27-G27,2)=0,"OK","REVIEW") -> OK
B28: C. MEMORANDA AND BASIS OF PREPARATION
B29: Memorandum item | G29: Amount (GHS)
B30: Output tax withheld at source by appointed VAT withholding agents (a payment credit, not a reduction of output tax) | G30: {=SUMPRODUCT((Ledger!$F$8:$F$307=$C$8)*(INDEX(Cat_Rate,MATCH(Ledger!$G$8:$G$307,Cat_Codes,0))=VAT_WHT_Rate)*Ledger!$H$8:$H$307*VAT_WHT_Rate)} -> 63364.63
B34: Basis of preparation and how to read this sheet
B35: 1. No category code is written into any formula on this sheet. Each sum tests the Ledger's Tax Category against the Categories sheet and reads the Charges VAT flag from there, so adding or reclassifying a category updates this reconciliation automatically.
B36: 2. The Direction filter is held in row 8 rather than inside the formulas. The Ledger records direction as Inflow and Outflow, so those are the values used; change row 8 if the Ledger's wording ever changes.
B37: 3. Rates are never typed here. Output and input tax are read from the Ledger's Expected VAT, Expected NHIL and Expected GETFund columns, which in turn read VAT_Rate, NHIL_Rate and GETFund_Rate on the Assumptions sheet.
B38: 4. Net VAT Payable is total output tax less total input tax. A negative figure means a net credit is due from the GRA. For a haulage company charging output tax on most of its revenue, that should be rare; an amber cell is a prompt to investigate, not a statement that something is wrong.
B39: 5. Input tax is gated on the Recoverable flag on the Categories sheet, not merely on Charges VAT. Tax incurred on non-recoverable categories is therefore excluded from columns F to H altogether, which is the correct treatment for a return. Control check 7 shows the amount excluded and proves it reconciles.
B40: 6. VAT withheld at source by appointed agents does not reduce output tax. It is a payment credit claimed on the return, shown as a memorandum only.

Sheet Error_Flags
B1: NKABOM HAULAGE LTD — CORE TAX ENGINE
B2: Sheet 5 of 6 • Error_Flags — Automated Exception Report • Simulated data
B3: Every flag is calculated from the Ledger. Nothing here is marked by hand. Change a test parameter in section A and the whole report re-runs.
B5: A. EXCEPTION TEST PARAMETERS — the only inputs on this sheet
B6: Categories where an invoice number is not required | F6: NO_VAT
B7: Categories excluded from the duplicate-invoice test | F7: WHT_GOODS | G7: WHT_WORKS | H7: VAT_WHT
B8: Tolerance on the tax comparison (GHS) | F8: 0.01
B9: Category prefix expected on money-in (Inflow) rows | F9: OUT_
B10: Category prefix expected on money-out (Outflow) rows | F10: IN_
B11: Categories subject to the keyword test | F11: IN_STD
B12: Keywords suggesting a non-recoverable or out-of-scope item | F12: salary | G12: salaries | H12: insurance | I12: fuel | J12: diesel | K12: petrol | L12: hospitality | M12: refreshment
B13: Add or remove keywords above — the Suspect Category test re-runs immediately. Matching ignores letter case and finds the keyword anywhere in the Description or Counterparty.
B15: B. SUMMARY — exceptions found
B16: Exception type | F16: Rows flagged | G16: Seeded in Error_Key | H16: Seeded rows actually detected | I16: Detection status
B17: Missing invoice number | F17: =COUNTIF($L$27:$L$326,"Yes") -> 3 | G17: =COUNTIF(tbl_ErrorKey[Error type],"Missing invoice number") -> 3 | H17: {=SUMPRODUCT((tbl_ErrorKey[Error type]="Missing invoice number")*(COUNTIFS($B$27:$B$326,tbl_ErrorKey[Row ID],$L$27:$L$326,"Yes")>0))} -> 3 | I17: =IF(H17=G17,"All "&G17&" seeded rows detected","Detects "&H17&" of "&G17&" seeded rows — "&G17-H17&" MISSED") -> All 3 seeded rows detected
B18: Duplicate invoice number | F18: =COUNTIF($M$27:$M$326,"Yes") -> 6 | G18: =COUNTIF(tbl_ErrorKey[Error type],"Duplicate invoice number") -> 3 | H18: {=SUMPRODUCT((tbl_ErrorKey[Error type]="Duplicate invoice number")*(COUNTIFS($B$27:$B$326,tbl_ErrorKey[Row ID],$M$27:$M$326,"Yes")>0))} -> 3 | I18: =IF(H18=G18,"All "&G18&" seeded rows detected","Detects "&H18&" of "&G18&" seeded rows — "&G18-H18&" MISSED") -> All 3 seeded rows detected
B19: Wrong tax amount | F19: =COUNTIF($N$27:$N$326,"Yes") -> 3 | G19: =COUNTIF(tbl_ErrorKey[Error type],"Wrong tax amount") -> 3 | H19: {=SUMPRODUCT((tbl_ErrorKey[Error type]="Wrong tax amount")*(COUNTIFS($B$27:$B$326,tbl_ErrorKey[Row ID],$N$27:$N$326,"Yes")>0))} -> 3 | I19: =IF(H19=G19,"All "&G19&" seeded rows detected","Detects "&H19&" of "&G19&" seeded rows — "&G19-H19&" MISSED") -> All 3 seeded rows detected
B20: Wrong category signal | F20: =COUNTIF($O$27:$O$326,"Yes") -> 0 | G20: =COUNTIF(tbl_ErrorKey[Error type],"Wrong tax category") -> 3 | H20: {=SUMPRODUCT((tbl_ErrorKey[Error type]="Wrong tax category")*(COUNTIFS($B$27:$B$326,tbl_ErrorKey[Row ID],$O$27:$O$326,"Yes")>0))} -> 0 | I20: =IF(F20=0,"No matching errors in this dataset — Direction/prefix consistent on all "&F23&" rows; the "&G20&" seeded category errors are caught by Suspect Category instead.",F20&" row(s) flagged — investigate") -> No matching errors in this dataset — Direction/prefix consistent on all 300 rows; the 3 seeded category errors are caught by Suspect Category instead.
B21: Suspect category (keyword test) | F21: =COUNTIF($P$27:$P$326,"Yes") -> 3 | G21: =COUNTIF(tbl_ErrorKey[Error type],"Wrong tax category") -> 3 | H21: {=SUMPRODUCT((tbl_ErrorKey[Error type]="Wrong tax category")*(COUNTIFS($B$27:$B$326,tbl_ErrorKey[Row ID],$P$27:$P$326,"Yes")>0))} -> 3 | I21: =IF(H21=G21,"All "&G21&" seeded rows detected","Detects "&H21&" of "&G21&" seeded rows — "&G21-H21&" MISSED") -> All 3 seeded rows detected | K21: =IF(H21=G21,"All "&G21&" seeded rows detected","Detects "&H21&" of "&G21&" seeded rows — "&G21-H21&" MISSED") -> All 3 seeded rows detected
B22: Total distinct rows flagged (Any Flag = Yes) | F22: =COUNTIF($Q$27:$Q$326,"Yes") -> 15 | G22: =ROWS(tbl_ErrorKey[Row ID]) -> 12 | H22: {=SUMPRODUCT((COUNTIFS($B$27:$B$326,tbl_ErrorKey[Row ID],$Q$27:$Q$326,"Yes")>0)*1)} -> 12 | I22: =IF(H22=G22,"All "&G22&" seeded rows detected","Detects "&H22&" of "&G22&" seeded rows — "&G22-H22&" MISSED") -> All 12 seeded rows detected | K22: =IF(F22=G22,"OK — every Ledger row is tested","REVIEW — row counts differ") -> REVIEW — row counts differ
B23: Rows tested (should equal the Ledger row count) | F23: =COUNTA($B$27:$B$326) -> 300 | G23: =ROWS(tbl_Ledger[Row ID]) -> 300 | H23: =F23 -> 300 | I23: =IF(F23=G23,"OK — every Ledger row is tested","REVIEW — row counts differ") -> OK — every Ledger row is tested
B24: C. EXCEPTION DETAIL — one row per Ledger transaction, 300 rows
C25: LEDGER EXTRACT — pulled from the Ledger, shown so each flag can be checked without leaving this sheet | L25: EXCEPTION FLAGS
B26: Row ID | C26: Date | D26: Invoice Number | E26: Tax Category | F26: Direction | G26: Tax Charged | H26: Expected Total Tax | I26: Description | J26: Counterparty | K26: In Duplicate Scope | L26: Missing Invoice | M26: Duplicate Invoice | N26: Wrong Tax Amount | O26: Wrong Category Signal | P26: Suspect Category | Q26: Any Flag
B27: {=INDEX(tbl_Ledger[Row ID],ROWS($B$27:$B27))} -> 1 | C27: {=INDEX(tbl_Ledger[Date],ROWS($B$27:$B27))} -> 46023 | D27: {=IF(INDEX(tbl_Ledger[Invoice Number],ROWS($B$27:$B27))="","",INDEX(tbl_Ledger[Invoice Number],ROWS($B$27:$B27)))} -> NHL-2026-0001 | E27: {=INDEX(tbl_Ledger[Tax Category],ROWS($B$27:$B27))} -> OUT_STD | F27: {=INDEX(tbl_Ledger[Direction],ROWS($B$27:$B27))} -> Inflow | G27: {=INDEX(tbl_Ledger[Tax Charged on Invoice],ROWS($B$27:$B27))} -> 3995.8 | H27: {=INDEX(tbl_Ledger[Expected Total Tax],ROWS($B$27:$B27))} -> 3995.8 | I27: {=INDEX(tbl_Ledger[Description],ROWS($B$27:$B27))} -> Bulk haulage of ATK, Kumasi-Sunyani, 9 trips | J27: {=INDEX(tbl_Ledger[Counterparty],ROWS($B$27:$B27))} -> Golden Harmattan Energy Ltd | K27: =IF(COUNTIF(Dup_Exclusions,$E27)>0,"No","Yes") -> Yes | L27: =IF(AND($D27="",COUNTIF(NoInv_Exempt,$E27)=0),"Yes","No") -> No | M27: {=IF(AND($D27<>"",$K27="Yes"),IF(SUMPRODUCT((tbl_Ledger[Invoice Number]=$D27)*(COUNTIF(Dup_Exclusions,tbl_Ledger[Tax Category])=0))>1,"Yes","No"),"No")} -> No | N27: =IF(ABS($G27-$H27)>Tax_Tolerance,"Yes","No") -> No | O27: =IF(OR(AND($F27="Inflow",LEFT($E27,LEN(Prefix_Outflow))=Prefix_Outflow),AND($F27="Outflow",LEFT($E27,LEN(Prefix_Inflow))=Prefix_Inflow)),"Yes","No") -> No | P27: {=IF(AND(COUNTIF(Suspect_Categories,$E27)>0,SUMPRODUCT(--ISNUMBER(SEARCH(Suspect_Keywords,$I27&" "&$J27)))>0),"Yes","No")} -> No | Q27: =IF(COUNTIF($L27:$P27,"Yes")>0,"Yes","No") -> No
B28: {=INDEX(tbl_Ledger[Row ID],ROWS($B$27:$B28))} -> 2 | C28: {=INDEX(tbl_Ledger[Date],ROWS($B$27:$B28))} -> 46025 | D28: {=IF(INDEX(tbl_Ledger[Invoice Number],ROWS($B$27:$B28))="","",INDEX(tbl_Ledger[Invoice Number],ROWS($B$27:$B28)))} -> NHL-2026-0002 | E28: {=INDEX(tbl_Ledger[Tax Category],ROWS($B$27:$B28))} -> OUT_STD | F28: {=INDEX(tbl_Ledger[Direction],ROWS($B$27:$B28))} -> Inflow | G28: {=INDEX(tbl_Ledger[Tax Charged on Invoice],ROWS($B$27:$B28))} -> 12648.4 | H28: {=INDEX(tbl_Ledger[Expected Total Tax],ROWS($B$27:$B28))} -> 12648.4 | I28: {=INDEX(tbl_Ledger[Description],ROWS($B$27:$B28))} -> Bulk haulage of ATK, Tema-Takoradi, 3 trips | J28: {=INDEX(tbl_Ledger[Counterparty],ROWS($B$27:$B28))} -> Tema Bulk Energy Ltd | K28: =IF(COUNTIF(Dup_Exclusions,$E28)>0,"No","Yes") -> Yes | L28: =IF(AND($D28="",COUNTIF(NoInv_Exempt,$E28)=0),"Yes","No") -> No | M28: {=IF(AND($D28<>"",$K28="Yes"),IF(SUMPRODUCT((tbl_Ledger[Invoice Number]=$D28)*(COUNTIF(Dup_Exclusions,tbl_Ledger[Tax Category])=0))>1,"Yes","No"),"No")} -> No | N28: =IF(ABS($G28-$H28)>Tax_Tolerance,"Yes","No") -> No | O28: =IF(OR(AND($F28="Inflow",LEFT($E28,LEN(Prefix_Outflow))=Prefix_Outflow),AND($F28="Outflow",LEFT($E28,LEN(Prefix_Inflow))=Prefix_Inflow)),"Yes","No") -> No | P28: {=IF(AND(COUNTIF(Suspect_Categories,$E28)>0,SUMPRODUCT(--ISNUMBER(SEARCH(Suspect_Keywords,$I28&" "&$J28)))>0),"Yes","No")} -> No | Q28: =IF(COUNTIF($L28:$P28,"Yes")>0,"Yes","No") -> No
B29: {=INDEX(tbl_Ledger[Row ID],ROWS($B$27:$B29))} -> 3 | C29: {=INDEX(tbl_Ledger[Date],ROWS($B$27:$B29))} -> 46026 | D29: {=IF(INDEX(tbl_Ledger[Invoice Number],ROWS($B$27:$B29))="","",INDEX(tbl_Ledger[Invoice Number],ROWS($B$27:$B29)))} -> SIN-2026-0001 | E29: {=INDEX(tbl_Ledger[Tax Category],ROWS($B$27:$B29))} -> IN_STD | F29: {=INDEX(tbl_Ledger[Direction],ROWS($B$27:$B29))} -> Outflow | G29: {=INDEX(tbl_Ledger[Tax Charged on Invoice],ROWS($B$27:$B29))} -> 334 | H29: {=INDEX(tbl_Ledger[Expected Total Tax],ROWS($B$27:$B29))} -> 334 | I29: {=INDEX(tbl_Ledger[Description],ROWS($B$27:$B29))} -> Mobile and data services | J29: {=INDEX(tbl_Ledger[Counterparty],ROWS($B$27:$B29))} -> Sahara Fleet Services Ltd | K29: =IF(COUNTIF(Dup_Exclusions,$E29)>0,"No","Yes") -> Yes | L29: =IF(AND($D29="",COUNTIF(NoInv_Exempt,$E29)=0),"Yes","No") -> No | M29: {=IF(AND($D29<>"",$K29="Yes"),IF(SUMPRODUCT((tbl_Ledger[Invoice Number]=$D29)*(COUNTIF(Dup_Exclusions,tbl_Ledger[Tax Category])=0))>1,"Yes","No"),"No")} -> No | N29: =IF(ABS($G29-$H29)>Tax_Tolerance,"Yes","No") -> No | O29: =IF(OR(AND($F29="Inflow",LEFT($E29,LEN(Prefix_Outflow))=Prefix_Outflow),AND($F29="Outflow",LEFT($E29,LEN(Prefix_Inflow))=Prefix_Inflow)),"Yes","No") -> No | P29: {=IF(AND(COUNTIF(Suspect_Categories,$E29)>0,SUMPRODUCT(--ISNUMBER(SEARCH(Suspect_Keywords,$I29&" "&$J29)))>0),"Yes","No")} -> No | Q29: =IF(COUNTIF($L29:$P29,"Yes")>0,"Yes","No") -> No
B30: {=INDEX(tbl_Ledger[Row ID],ROWS($B$27:$B30))} -> 4 | C30: {=INDEX(tbl_Ledger[Date],ROWS($B$27:$B30))} -> 46027 | D30: {=IF(INDEX(tbl_Ledger[Invoice Number],ROWS($B$27:$B30))="","",INDEX(tbl_Ledger[Invoice Number],ROWS($B$27:$B30)))} -> NHL-2026-0003 | E30: {=INDEX(tbl_Ledger[Tax Category],ROWS($B$27:$B30))} -> WHT_SVC | F30: {=INDEX(tbl_Ledger[Direction],ROWS($B$27:$B30))} -> Inflow | G30: {=INDEX(tbl_Ledger[Tax Charged on Invoice],ROWS($B$27:$B30))} -> 13722.8 | H30: {=INDEX(tbl_Ledger[Expected Total Tax],ROWS($B$27:$B30))} -> 13722.8 | I30: {=INDEX(tbl_Ledger[Description],ROWS($B$27:$B30))} -> Contract haulage of PMS, Tema-Ho; customer withheld income tax at 7.5% on the service fee | J30: {=INDEX(tbl_Ledger[Counterparty],ROWS($B$27:$B30))} -> Tema Bulk Energy Ltd | K30: =IF(COUNTIF(Dup_Exclusions,$E30)>0,"No","Yes") -> Yes | L30: =IF(AND($D30="",COUNTIF(NoInv_Exempt,$E30)=0),"Yes","No") -> No | M30: {=IF(AND($D30<>"",$K30="Yes"),IF(SUMPRODUCT((tbl_Ledger[Invoice Number]=$D30)*(COUNTIF(Dup_Exclusions,tbl_Ledger[Tax Category])=0))>1,"Yes","No"),"No")} -> No | N30: =IF(ABS($G30-$H30)>Tax_Tolerance,"Yes","No") -> No | O30: =IF(OR(AND($F30="Inflow",LEFT($E30,LEN(Prefix_Outflow))=Prefix_Outflow),AND($F30="Outflow",LEFT($E30,LEN(Prefix_Inflow))=Prefix_Inflow)),"Yes","No") -> No | P30: {=IF(AND(COUNTIF(Suspect_Categories,$E30)>0,SUMPRODUCT(--ISNUMBER(SEARCH(Suspect_Keywords,$I30&" "&$J30)))>0),"Yes","No")} -> No | Q30: =IF(COUNTIF($L30:$P30,"Yes")>0,"Yes","No") -> No
B31: {=INDEX(tbl_Ledger[Row ID],ROWS($B$27:$B31))} -> 5 | C31: {=INDEX(tbl_Ledger[Date],ROWS($B$27:$B31))} -> 46028 | D31: {=IF(INDEX(tbl_Ledger[Invoice Number],ROWS($B$27:$B31))="","",INDEX(tbl_Ledger[Invoice Number],ROWS($B$27:$B31)))} -> NHL-2026-0004 | E31: {=INDEX(tbl_Ledger[Tax Category],ROWS($B$27:$B31))} -> OUT_STD | F31: {=INDEX(tbl_Ledger[Direction],ROWS($B$27:$B31))} -> Inflow | G31: {=INDEX(tbl_Ledger[Tax Charged on Invoice],ROWS($B$27:$B31))} -> 13309.4 | H31: {=INDEX(tbl_Ledger[Expected Total Tax],ROWS($B$27:$B31))} -> 13309.4 | I31: {=INDEX(tbl_Ledger[Description],ROWS($B$27:$B31))} -> Bulk haulage of AGO, Tema-Bolgatanga, 2 trips | J31: {=INDEX(tbl_Ledger[Counterparty],ROWS($B$27:$B31))} -> Sankofa Petroleum Depot Ltd | K31: =IF(COUNTIF(Dup_Exclusions,$E31)>0,"No","Yes") -> Yes | L31: =IF(AND($D31="",COUNTIF(NoInv_Exempt,$E31)=0),"Yes","No") -> No | M31: {=IF(AND($D31<>"",$K31="Yes"),IF(SUMPRODUCT((tbl_Ledger[Invoice Number]=$D31)*(COUNTIF(Dup_Exclusions,tbl_Ledger[Tax Category])=0))>1,"Yes","No"),"No")} -> No | N31: =IF(ABS($G31-$H31)>Tax_Tolerance,"Yes","No") -> No | O31: =IF(OR(AND($F31="Inflow",LEFT($E31,LEN(Prefix_Outflow))=Prefix_Outflow),AND($F31="Outflow",LEFT($E31,LEN(Prefix_Inflow))=Prefix_Inflow)),"Yes","No") -> No | P31: {=IF(AND(COUNTIF(Suspect_Categories,$E31)>0,SUMPRODUCT(--ISNUMBER(SEARCH(Suspect_Keywords,$I31&" "&$J31)))>0),"Yes","No")} -> No | Q31: =IF(COUNTIF($L31:$P31,"Yes")>0,"Yes","No") -> No
B32: {=INDEX(tbl_Ledger[Row ID],ROWS($B$27:$B32))} -> 6 | C32: {=INDEX(tbl_Ledger[Date],ROWS($B$27:$B32))} -> 46028 | D32: {=IF(INDEX(tbl_Ledger[Invoice Number],ROWS($B$27:$B32))="","",INDEX(tbl_Ledger[Invoice Number],ROWS($B$27:$B32)))} -> NHL-2026-0005 | E32: {=INDEX(tbl_Ledger[Tax Category],ROWS($B$27:$B32))} -> WHT_SVC | F32: {=INDEX(tbl_Ledger[Direction],ROWS($B$27:$B32))} -> Inflow | G32: {=INDEX(tbl_Ledger[Tax Charged on Invoice],ROWS($B$27:$B32))} -> 11735.6 | H32: {=INDEX(tbl_Ledger[Expected Total Tax],ROWS($B$27:$B32))} -> 11735.6 | I32: {=INDEX(tbl_Ledger[Description],ROWS($B$27:$B32))} -> Contract haulage of AGO, Tema-Bolgatanga; customer withheld income tax at 7.5% on the service fee | J32: {=INDEX(tbl_Ledger[Counterparty],ROWS($B$27:$B32))} -> Tema Bulk Energy Ltd | K32: =IF(COUNTIF(Dup_Exclusions,$E32)>0,"No","Yes") -> Yes | L32: =IF(AND($D32="",COUNTIF(NoInv_Exempt,$E32)=0),"Yes","No") -> No | M32: {=IF(AND($D32<>"",$K32="Yes"),IF(SUMPRODUCT((tbl_Ledger[Invoice Number]=$D32)*(COUNTIF(Dup_Exclusions,tbl_Ledger[Tax Category])=0))>1,"Yes","No"),"No")} -> No | N32: =IF(ABS($G32-$H32)>Tax_Tolerance,"Yes","No") -> No | O32: =IF(OR(AND($F32="Inflow",LEFT($E32,LEN(Prefix_Outflow))=Prefix_Outflow),AND($F32="Outflow",LEFT($E32,LEN(Prefix_Inflow))=Prefix_Inflow)),"Yes","No") -> No | P32: {=IF(AND(COUNTIF(Suspect_Categories,$E32)>0,SUMPRODUCT(--ISNUMBER(SEARCH(Suspect_Keywords,$I32&" "&$J32)))>0),"Yes","No")} -> No | Q32: =IF(COUNTIF($L32:$P32,"Yes")>0,"Yes","No") -> No
B33: {=INDEX(tbl_Ledger[Row ID],ROWS($B$27:$B33))} -> 7 | C33: {=INDEX(tbl_Ledger[Date],ROWS($B$27:$B33))} -> 46029 | D33: {=IF(INDEX(tbl_Ledger[Invoice Number],ROWS($B$27:$B33))="","",INDEX(tbl_Ledger[Invoice Number],ROWS($B$27:$B33)))} -> NHL-2026-0006 | E33: {=INDEX(tbl_Ledger[Tax Category],ROWS($B$27:$B33))} -> OUT_STD | F33: {=INDEX(tbl_Ledger[Direction],ROWS($B$27:$B33))} -> Inflow | G33: {=INDEX(tbl_Ledger[Tax Charged on Invoice],ROWS($B$27:$B33))} -> 18186.6 | H33: {=INDEX(tbl_Ledger[Expected Total Tax],ROWS($B$27:$B33))} -> 18186.6 | I33: {=INDEX(tbl_Ledger[Description],ROWS($B$27:$B33))} -> Bulk haulage of AGO, Takoradi-Wa, 7 trips | J33: {=INDEX(tbl_Ledger[Counterparty],ROWS($B$27:$B33))} -> Golden Harmattan Energy Ltd | K33: =IF(COUNTIF(Dup_Exclusions,$E33)>0,"No","Yes") -> Yes | L33: =IF(AND($D33="",COUNTIF(NoInv_Exempt,$E33)=0),"Yes","No") -> No | M33: {=IF(AND($D33<>"",$K33="Yes"),IF(SUMPRODUCT((tbl_Ledger[Invoice Number]=$D33)*(COUNTIF(Dup_Exclusions,tbl_Ledger[Tax Category])=0))>1,"Yes","No"),"No")} -> No | N33: =IF(ABS($G33-$H33)>Tax_Tolerance,"Yes","No") -> No | O33: =IF(OR(AND($F33="Inflow",LEFT($E33,LEN(Prefix_Outflow))=Prefix_Outflow),AND($F33="Outflow",LEFT($E33,LEN(Prefix_Inflow))=Prefix_Inflow)),"Yes","No") -> No | P33: {=IF(AND(COUNTIF(Suspect_Categories,$E33)>0,SUMPRODUCT(--ISNUMBER(SEARCH(Suspect_Keywords,$I33&" "&$J33)))>0),"Yes","No")} -> No | Q33: =IF(COUNTIF($L33:$P33,"Yes")>0,"Yes","No") -> No
B34: {=INDEX(tbl_Ledger[Row ID],ROWS($B$27:$B34))} -> 8 | C34: {=INDEX(tbl_Ledger[Date],ROWS($B$27:$B34))} -> 46032 | D34: {=IF(INDEX(tbl_Ledger[Invoice Number],ROWS($B$27:$B34))="","",INDEX(tbl_Ledger[Invoice Number],ROWS($B$27:$B34)))} -> SIN-2026-0002 | E34: {=INDEX(tbl_Ledger[Tax Category],ROWS($B$27:$B34))} -> IN_EXEMPT | F34: {=INDEX(tbl_Ledger[Direction],ROWS($B$27:$B34))} -> Outflow | G34: {=INDEX(tbl_Ledger[Tax Charged on Invoice],ROWS($B$27:$B34))} -> 0 | H34: {=INDEX(tbl_Ledger[Expected Total Tax],ROWS($B$27:$B34))} -> 0 | I34: {=INDEX(tbl_Ledger[Description],ROWS($B$27:$B34))} -> Diesel (AGO) purchased for own fleet use, 10,136 litres | J34: {=INDEX(tbl_Ledger[Counterparty],ROWS($B$27:$B34))} -> Zenith Fuel Depot Ltd | K34: =IF(COUNTIF(Dup_Exclusions,$E34)>0,"No","Yes") -> Yes | L34: =IF(AND($D34="",COUNTIF(NoInv_Exempt,$E34)=0),"Yes","No") -> No | M34: {=IF(AND($D34<>"",$K34="Yes"),IF(SUMPRODUCT((tbl_Ledger[Invoice Number]=$D34)*(COUNTIF(Dup_Exclusions,tbl_Ledger[Tax Category])=0))>1,"Yes","No"),"No")} -> No | N34: =IF(ABS($G34-$H34)>Tax_Tolerance,"Yes","No") -> No | O34: =IF(OR(AND($F34="Inflow",LEFT($E34,LEN(Prefix_Outflow))=Prefix_Outflow),AND($F34="Outflow",LEFT($E34,LEN(Prefix_Inflow))=Prefix_Inflow)),"Yes","No") -> No | P34: {=IF(AND(COUNTIF(Suspect_Categories,$E34)>0,SUMPRODUCT(--ISNUMBER(SEARCH(Suspect_Keywords,$I34&" "&$J34)))>0),"Yes","No")} -> No | Q34: =IF(COUNTIF($L34:$P34,"Yes")>0,"Yes","No") -> No
B35: {=INDEX(tbl_Ledger[Row ID],ROWS($B$27:$B35))} -> 9 | C35: {=INDEX(tbl_Ledger[Date],ROWS($B$27:$B35))} -> 46032 | D35: {=IF(INDEX(tbl_Ledger[Invoice Number],ROWS($B$27:$B35))="","",INDEX(tbl_Ledger[Invoice Number],ROWS($B$27:$B35)))} -> SIN-2026-0003 | E35: {=INDEX(tbl_Ledger[Tax Category],ROWS($B$27:$B35))} -> IN_EXEMPT | F35: {=INDEX(tbl_Ledger[Direction],ROWS($B$27:$B35))} -> Outflow | G35: {=INDEX(tbl_Ledger[Tax Charged on Invoice],ROWS($B$27:$B35))} -> 0 | H35: {=INDEX(tbl_Ledger[Expected Total Tax],ROWS($B$27:$B35))} -> 0 | I35: {=INDEX(tbl_Ledger[Description],ROWS($B$27:$B35))} -> Diesel (AGO) purchased for own fleet use, 8,242 litres | J35: {=INDEX(tbl_Ledger[Counterparty],ROWS($B$27:$B35))} -> Zenith Fuel Depot Ltd | K35: =IF(COUNTIF(Dup_Exclusions,$E35)>0,"No","Yes") -> Yes | L35: =IF(AND($D35="",COUNTIF(NoInv_Exempt,$E35)=0),"Yes","No") -> No | M35: {=IF(AND($D35<>"",$K35="Yes"),IF(SUMPRODUCT((tbl_Ledger[Invoice Number]=$D35)*(COUNTIF(Dup_Exclusions,tbl_Ledger[Tax Category])=0))>1,"Yes","No"),"No")} -> No | N35: =IF(ABS($G35-$H35)>Tax_Tolerance,"Yes","No") -> No | O35: =IF(OR(AND($F35="Inflow",LEFT($E35,LEN(Prefix_Outflow))=Prefix_Outflow),AND($F35="Outflow",LEFT($E35,LEN(Prefix_Inflow))=Prefix_Inflow)),"Yes","No") -> No | P35: {=IF(AND(COUNTIF(Suspect_Categories,$E35)>0,SUMPRODUCT(--ISNUMBER(SEARCH(Suspect_Keywords,$I35&" "&$J35)))>0),"Yes","No")} -> No | Q35: =IF(COUNTIF($L35:$P35,"Yes")>0,"Yes","No") -> No
B36: {=INDEX(tbl_Ledger[Row ID],ROWS($B$27:$B36))} -> 10 | C36: {=INDEX(tbl_Ledger[Date],ROWS($B$27:$B36))} -> 46034 | D36: {=IF(INDEX(tbl_Ledger[Invoice Number],ROWS($B$27:$B36))="","",INDEX(tbl_Ledger[Invoice Number],ROWS($B$27:$B36)))} -> SIN-2026-0004 | E36: {=INDEX(tbl_Ledger[Tax Category],ROWS($B$27:$B36))} -> IN_EXEMPT | F36: {=INDEX(tbl_Ledger[Direction],ROWS($B$27:$B36))} -> Outflow | G36: {=INDEX(tbl_Ledger[Tax Charged on Invoice],ROWS($B$27:$B36))} -> 0 | H36: {=INDEX(tbl_Ledger[Expected Total Tax],ROWS($B$27:$B36))} -> 0 | I36: {=INDEX(tbl_Ledger[Description],ROWS($B$27:$B36))} -> Diesel (AGO) purchased for own fleet use, 16,629 litres | J36: {=INDEX(tbl_Ledger[Counterparty],ROWS($B$27:$B36))} -> Zenith Fuel Depot Ltd | K36: =IF(COUNTIF(Dup_Exclusions,$E36)>0,"No","Yes") -> Yes | L36: =IF(AND($D36="",COUNTIF(NoInv_Exempt,$E36)=0),"Yes","No") -> No | M36: {=IF(AND($D36<>"",$K36="Yes"),IF(SUMPRODUCT((tbl_Ledger[Invoice Number]=$D36)*(COUNTIF(Dup_Exclusions,tbl_Ledger[Tax Category])=0))>1,"Yes","No"),"No")} -> No | N36: =IF(ABS($G36-$H36)>Tax_Tolerance,"Yes","No") -> No | O36: =IF(OR(AND($F36="Inflow",LEFT($E36,LEN(Prefix_Outflow))=Prefix_Outflow),AND($F36="Outflow",LEFT($E36,LEN(Prefix_Inflow))=Prefix_Inflow)),"Yes","No") -> No | P36: {=IF(AND(COUNTIF(Suspect_Categories,$E36)>0,SUMPRODUCT(--ISNUMBER(SEARCH(Suspect_Keywords,$I36&" "&$J36)))>0),"Yes","No")} -> No | Q36: =IF(COUNTIF($L36:$P36,"Yes")>0,"Yes","No") -> No
B37: {=INDEX(tbl_Ledger[Row ID],ROWS($B$27:$B37))} -> 11 | C37: {=INDEX(tbl_Ledger[Date],ROWS($B$27:$B37))} -> 46036 | D37: {=IF(INDEX(tbl_Ledger[Invoice Number],ROWS($B$27:$B37))="","",INDEX(tbl_Ledger[Invoice Number],ROWS($B$27:$B37)))} -> GRA-2026-0001 | E37: {=INDEX(tbl_Ledger[Tax Category],ROWS($B$27:$B37))} -> NO_VAT | F37: {=INDEX(tbl_Ledger[Direction],ROWS($B$27:$B37))} -> Outflow | G37: {=INDEX(tbl_Ledger[Tax Charged on Invoice],ROWS($B$27:$B37))} -> 0 | H37: {=INDEX(tbl_Ledger[Expected Total Tax],ROWS($B$27:$B37))} -> 0 | I37: {=INDEX(tbl_Ledger[Description],ROWS($B$27:$B37))} -> PAYE and SSNIT contributions - January | J37: {=INDEX(tbl_Ledger[Counterparty],ROWS($B$27:$B37))} -> Ghana Revenue Authority | K37: =IF(COUNTIF(Dup_Exclusions,$E37)>0,"No","Yes") -> Yes | L37: =IF(AND($D37="",COUNTIF(NoInv_Exempt,$E37)=0),"Yes","No") -> No | M37: {=IF(AND($D37<>"",$K37="Yes"),IF(SUMPRODUCT((tbl_Ledger[Invoice Number]=$D37)*(COUNTIF(Dup_Exclusions,tbl_Ledger[Tax Category])=0))>1,"Yes","No"),"No")} -> No | N37: =IF(ABS($G37-$H37)>Tax_Tolerance,"Yes","No") -> No | O37: =IF(OR(AND($F37="Inflow",LEFT($E37,LEN(Prefix_Outflow))=Prefix_Outflow),AND($F37="Outflow",LEFT($E37,LEN(Prefix_Inflow))=Prefix_Inflow)),"Yes","No") -> No | P37: {=IF(AND(COUNTIF(Suspect_Categories,$E37)>0,SUMPRODUCT(--ISNUMBER(SEARCH(Suspect_Keywords,$I37&" "&$J37)))>0),"Yes","No")} -> No | Q37: =IF(COUNTIF($L37:$P37,"Yes")>0,"Yes","No") -> No
B38: {=INDEX(tbl_Ledger[Row ID],ROWS($B$27:$B38))} -> 12 | C38: {=INDEX(tbl_Ledger[Date],ROWS($B$27:$B38))} -> 46037 | D38: {=IF(INDEX(tbl_Ledger[Invoice Number],ROWS($B$27:$B38))="","",INDEX(tbl_Ledger[Invoice Number],ROWS($B$27:$B38)))} -> LN-2026-0001 | E38: {=INDEX(tbl_Ledger[Tax Category],ROWS($B$27:$B38))} -> NO_VAT | F38: {=INDEX(tbl_Ledger[Direction],ROWS($B$27:$B38))} -> Outflow | G38: {=INDEX(tbl_Ledger[Tax Charged on Invoice],ROWS($B$27:$B38))} -> 0 | H38: {=INDEX(tbl_Ledger[Expected Total Tax],ROWS($B$27:$B38))} -> 0 | I38: {=INDEX(tbl_Ledger[Description],ROWS($B$27:$B38))} -> Term loan repayment - principal and interest, instalment 1 | J38: {=INDEX(tbl_Ledger[Counterparty],ROWS($B$27:$B38))} -> Meridian Bank Ghana Ltd | K38: =IF(COUNTIF(Dup_Exclusions,$E38)>0,"No","Yes") -> Yes | L38: =IF(AND($D38="",COUNTIF(NoInv_Exempt,$E38)=0),"Yes","No") -> No | M38: {=IF(AND($D38<>"",$K38="Yes"),IF(SUMPRODUCT((tbl_Ledger[Invoice Number]=$D38)*(COUNTIF(Dup_Exclusions,tbl_Ledger[Tax Category])=0))>1,"Yes","No"),"No")} -> No | N38: =IF(ABS($G38-$H38)>Tax_Tolerance,"Yes","No") -> No | O38: =IF(OR(AND($F38="Inflow",LEFT($E38,LEN(Prefix_Outflow))=Prefix_Outflow),AND($F38="Outflow",LEFT($E38,LEN(Prefix_Inflow))=Prefix_Inflow)),"Yes","No") -> No | P38: {=IF(AND(COUNTIF(Suspect_Categories,$E38)>0,SUMPRODUCT(--ISNUMBER(SEARCH(Suspect_Keywords,$I38&" "&$J38)))>0),"Yes","No")} -> No | Q38: =IF(COUNTIF($L38:$P38,"Yes")>0,"Yes","No") -> No
... B326: {=INDEX(tbl_Ledger[Row ID],ROWS($B$27:$B326))} -> 300 | C326: {=INDEX(tbl_Ledger[Date],ROWS($B$27:$B326))} -> 46265 | D326: {=IF(INDEX(tbl_Ledger[Invoice Number],ROWS($B$27:$B326))="","",INDEX(tbl_Ledger[Invoice Number],ROWS($B$27:$B326)))} -> NHL-2026-0113 | E326: {=INDEX(tbl_Ledger[Tax Category],ROWS($B$27:$B326))} -> OUT_STD | F326: {=INDEX(tbl_Ledger[Direction],ROWS($B$27:$B326))} -> Inflow | G326: {=INDEX(tbl_Ledger[Tax Charged on Invoice],ROWS($B$27:$B326))} -> 6667.4 | H326: {=INDEX(tbl_Ledger[Expected Total Tax],ROWS($B$27:$B326))} -> 6667.4 | I326: {=INDEX(tbl_Ledger[Description],ROWS($B$27:$B326))} -> Bulk haulage of LPG, Tema-Ho, 3 trips | J326: {=INDEX(tbl_Ledger[Counterparty],ROWS($B$27:$B326))} -> Golden Harmattan Energy Ltd | K326: =IF(COUNTIF(Dup_Exclusions,$E326)>0,"No","Yes") -> Yes | L326: =IF(AND($D326="",COUNTIF(NoInv_Exempt,$E326)=0),"Yes","No") -> No | M326: {=IF(AND($D326<>"",$K326="Yes"),IF(SUMPRODUCT((tbl_Ledger[Invoice Number]=$D326)*(COUNTIF(Dup_Exclusions,tbl_Ledger[Tax Category])=0))>1,"Yes","No"),"No")} -> No | N326: =IF(ABS($G326-$H326)>Tax_Tolerance,"Yes","No") -> No | O326: =IF(OR(AND($F326="Inflow",LEFT($E326,LEN(Prefix_Outflow))=Prefix_Outflow),AND($F326="Outflow",LEFT($E326,LEN(Prefix_Inflow))=Prefix_Inflow)),"Yes","No") -> No | P326: {=IF(AND(COUNTIF(Suspect_Categories,$E326)>0,SUMPRODUCT(--ISNUMBER(SEARCH(Suspect_Keywords,$I326&" "&$J326)))>0),"Yes","No")} -> No | Q326: =IF(COUNTIF($L326:$P326,"Yes")>0,"Yes","No") -> No

Sheet Cash_Flow
B1: NKABOM HAULAGE LTD — CORE TAX ENGINE
B2: Sheet 6 of 6 • Cash_Flow — Monthly Cash Flow Summary • All amounts in GHS • Simulated data
B3: Cash movements are the tax-exclusive Amount column of the Ledger, split by Direction. Every figure is a formula reading the Ledger table; only the cells shaded cream are inputs.
B5: A. OPENING POSITION AND PARAMETERS — the only inputs on this sheet
B6: Opening cash balance at the start of the period (GHS) | F6: 0 | H6: January's Opening Balance reads this cell. Set it to the actual bank position to run the sheet on real data.
B7: Ledger Direction label for money in | F7: Inflow
B8: Ledger Direction label for money out | F8: Outflow
B9: Tax authority counterparty name, as recorded in the Ledger | F9: Ghana Revenue Authority
B10: Description keywords identifying a tax remittance | F10: remitted | G10: PAYE | H10: Both words are matched anywhere in the Ledger Description, ignoring case.
B12: B. MONTHLY CASH FLOW — January to August of the ledger year
B13: Month | C13: Inflows | D13: Outflows | E13: Net Cash Flow | F13: Opening Balance | G13: Closing Balance | H13: Sense check
B14: Ledger Direction filter applied → | C14: =Dir_In -> Inflow | D14: =Dir_Out -> Outflow
B15: =DATE(Ledger_Year,1,1) -> 46023 | C15: {=SUMPRODUCT((YEAR(tbl_Ledger[Date])=YEAR($B15))*(MONTH(tbl_Ledger[Date])=MONTH($B15))*(tbl_Ledger[Direction]=C$14)*tbl_Ledger[Amount])} -> 1301076 | D15: {=SUMPRODUCT((YEAR(tbl_Ledger[Date])=YEAR($B15))*(MONTH(tbl_Ledger[Date])=MONTH($B15))*(tbl_Ledger[Direction]=D$14)*tbl_Ledger[Amount])} -> 690006 | E15: =C15-D15 -> 611070 | F15: =Opening_Cash -> 0 | G15: =F15+E15 -> 611070 | H15: =IF(E15<0,"Negative net cash flow — review","OK") -> OK
B16: =EDATE(B15,1) -> 46054 | C16: {=SUMPRODUCT((YEAR(tbl_Ledger[Date])=YEAR($B16))*(MONTH(tbl_Ledger[Date])=MONTH($B16))*(tbl_Ledger[Direction]=C$14)*tbl_Ledger[Amount])} -> 899759 | D16: {=SUMPRODUCT((YEAR(tbl_Ledger[Date])=YEAR($B16))*(MONTH(tbl_Ledger[Date])=MONTH($B16))*(tbl_Ledger[Direction]=D$14)*tbl_Ledger[Amount])} -> 639828 | E16: =C16-D16 -> 259931 | F16: =G15 -> 611070 | G16: =F16+E16 -> 871001 | H16: =IF(E16<0,"Negative net cash flow — review","OK") -> OK
B17: =EDATE(B16,1) -> 46082 | C17: {=SUMPRODUCT((YEAR(tbl_Ledger[Date])=YEAR($B17))*(MONTH(tbl_Ledger[Date])=MONTH($B17))*(tbl_Ledger[Direction]=C$14)*tbl_Ledger[Amount])} -> 1060486 | D17: {=SUMPRODUCT((YEAR(tbl_Ledger[Date])=YEAR($B17))*(MONTH(tbl_Ledger[Date])=MONTH($B17))*(tbl_Ledger[Direction]=D$14)*tbl_Ledger[Amount])} -> 629109 | E17: =C17-D17 -> 431377 | F17: =G16 -> 871001 | G17: =F17+E17 -> 1302378 | H17: =IF(E17<0,"Negative net cash flow — review","OK") -> OK
B18: =EDATE(B17,1) -> 46113 | C18: {=SUMPRODUCT((YEAR(tbl_Ledger[Date])=YEAR($B18))*(MONTH(tbl_Ledger[Date])=MONTH($B18))*(tbl_Ledger[Direction]=C$14)*tbl_Ledger[Amount])} -> 751592 | D18: {=SUMPRODUCT((YEAR(tbl_Ledger[Date])=YEAR($B18))*(MONTH(tbl_Ledger[Date])=MONTH($B18))*(tbl_Ledger[Direction]=D$14)*tbl_Ledger[Amount])} -> 503061 | E18: =C18-D18 -> 248531 | F18: =G17 -> 1302378 | G18: =F18+E18 -> 1550909 | H18: =IF(E18<0,"Negative net cash flow — review","OK") -> OK
B19: =EDATE(B18,1) -> 46143 | C19: {=SUMPRODUCT((YEAR(tbl_Ledger[Date])=YEAR($B19))*(MONTH(tbl_Ledger[Date])=MONTH($B19))*(tbl_Ledger[Direction]=C$14)*tbl_Ledger[Amount])} -> 745602 | D19: {=SUMPRODUCT((YEAR(tbl_Ledger[Date])=YEAR($B19))*(MONTH(tbl_Ledger[Date])=MONTH($B19))*(tbl_Ledger[Direction]=D$14)*tbl_Ledger[Amount])} -> 689270 | E19: =C19-D19 -> 56332 | F19: =G18 -> 1550909 | G19: =F19+E19 -> 1607241 | H19: =IF(E19<0,"Negative net cash flow — review","OK") -> OK
B20: =EDATE(B19,1) -> 46174 | C20: {=SUMPRODUCT((YEAR(tbl_Ledger[Date])=YEAR($B20))*(MONTH(tbl_Ledger[Date])=MONTH($B20))*(tbl_Ledger[Direction]=C$14)*tbl_Ledger[Amount])} -> 736397 | D20: {=SUMPRODUCT((YEAR(tbl_Ledger[Date])=YEAR($B20))*(MONTH(tbl_Ledger[Date])=MONTH($B20))*(tbl_Ledger[Direction]=D$14)*tbl_Ledger[Amount])} -> 1095566 | E20: =C20-D20 -> -359169 | F20: =G19 -> 1607241 | G20: =F20+E20 -> 1248072 | H20: =IF(E20<0,"Negative net cash flow — review","OK") -> Negative net cash flow — review
B21: =EDATE(B20,1) -> 46204 | C21: {=SUMPRODUCT((YEAR(tbl_Ledger[Date])=YEAR($B21))*(MONTH(tbl_Ledger[Date])=MONTH($B21))*(tbl_Ledger[Direction]=C$14)*tbl_Ledger[Amount])} -> 853161 | D21: {=SUMPRODUCT((YEAR(tbl_Ledger[Date])=YEAR($B21))*(MONTH(tbl_Ledger[Date])=MONTH($B21))*(tbl_Ledger[Direction]=D$14)*tbl_Ledger[Amount])} -> 581821 | E21: =C21-D21 -> 271340 | F21: =G20 -> 1248072 | G21: =F21+E21 -> 1519412 | H21: =IF(E21<0,"Negative net cash flow — review","OK") -> OK
B22: =EDATE(B21,1) -> 46235 | C22: {=SUMPRODUCT((YEAR(tbl_Ledger[Date])=YEAR($B22))*(MONTH(tbl_Ledger[Date])=MONTH($B22))*(tbl_Ledger[Direction]=C$14)*tbl_Ledger[Amount])} -> 1094702 | D22: {=SUMPRODUCT((YEAR(tbl_Ledger[Date])=YEAR($B22))*(MONTH(tbl_Ledger[Date])=MONTH($B22))*(tbl_Ledger[Direction]=D$14)*tbl_Ledger[Amount])} -> 633839 | E22: =C22-D22 -> 460863 | F22: =G21 -> 1519412 | G22: =F22+E22 -> 1980275 | H22: =IF(E22<0,"Negative net cash flow — review","OK") -> OK
B23: TOTAL Jan–Aug | C23: =SUM(C15:C22) -> 7442775 | D23: =SUM(D15:D22) -> 5462500 | E23: =SUM(E15:E22) -> 1980275 | F23: =F15 -> 0 | G23: {=INDEX(G15:G22,COUNT(B15:B22))} -> 1980275 | H23: =IF(ROUND(F23+E23-G23,2)=0,"OK — opening plus net movement equals closing","REVIEW — roll-forward does not tie") -> OK — opening plus net movement equals closing
B25: C. TAX MEMORANDUM — tax flows relating to the period, shown separately from cash
B26: Memorandum item | G26: Amount (GHS)
B27: Total tax collected on sales (output VAT, NHIL and GETFund per VAT_Recon) | G27: {=VR_Output_Tax_Total} -> 1488555
B28: Total tax paid to GRA in the period (VAT and levy remittances, PAYE and SSNIT, and withholding tax remitted) | G28: {=SUMPRODUCT((tbl_Ledger[Counterparty]=Tax_Authority)*(tbl_Ledger[Direction]=Dir_Out)*SIGN(--ISNUMBER(SEARCH(Remit_Kw1,tbl_Ledger[Description]))+--ISNUMBER(SEARCH(Remit_Kw2,tbl_Ledger[Description])))*tbl_Ledger[Amount])} -> 682003
B29: Total tax withheld at source by appointed VAT withholding agents (per VAT_Recon memo) | G29: =VR_Withheld_At_Source -> 63364.63
B30: Tax collected but not yet settled (collected, less paid, less withheld at source) | G30: =G27-G28-G29 -> 743187.37
B33: D. CONTROL CHECKS
B34: Control check | E34: Expected | F34: Actual | G34: Status
B35: 1. Inflows plus outflows equal the total Amount recorded in the Ledger | E35: =SUM(tbl_Ledger[Amount]) -> 12905275 | F35: =C23+D23 -> 12905275 | G35: =IF(ROUND(E35-F35,2)=0,"OK","REVIEW") -> OK
B36: 2. Every Ledger transaction falls inside the months reported here | E36: =ROWS(tbl_Ledger[Row ID]) -> 300 | F36: {=SUMPRODUCT((tbl_Ledger[Date]>=$B$15)*(tbl_Ledger[Date]<=EOMONTH(INDEX($B$15:$B$22,COUNT($B$15:$B$22)),0))*1)} -> 300 | G36: =IF(E36=F36,"OK","REVIEW") -> OK
B37: 3. Every Ledger row carries one of the two Direction labels in section A | E37: =ROWS(tbl_Ledger[Row ID]) -> 300 | F37: {=SUMPRODUCT(((tbl_Ledger[Direction]=Dir_In)+(tbl_Ledger[Direction]=Dir_Out))*1)} -> 300 | G37: =IF(E37=F37,"OK","REVIEW") -> OK
B38: 4. Closing balance equals the opening balance plus total net cash flow | E38: =Opening_Cash+E23 -> 1980275 | F38: =G23 -> 1980275 | G38: =IF(ROUND(E38-F38,2)=0,"OK","REVIEW") -> OK
B39: 5. Eight distinct months are reported, with no gaps | E39: 8 | F39: =COUNT($B$15:$B$22) -> 8 | G39: =IF(E39=F39,"OK","REVIEW") -> OK
B41: E. BASIS OF PREPARATION
B42: 1. Inflows and outflows are the tax-exclusive Amount column of the Ledger, split by the Direction labels held in section A. They are not the gross invoiced amounts, so the totals here will not equal the Gross Amount column of the Ledger.
B43: 2. Months are generated from the Ledger year on the Assumptions sheet. January reads the Opening Balance input; every later month reads the preceding month's Closing Balance, so the roll-forward is continuous and control check 4 proves it ties.
B44: 3. A negative Net Cash Flow is flagged amber as a sense check, not as an error. A haulage business can legitimately have a cash-negative month when fleet costs, payroll and loan instalments fall together.
B45: 4. Tax paid to GRA is summed from the Ledger itself: outflows to the counterparty named in section A whose description contains either remittance keyword held there. On the current data it captures 18 rows — eight monthly VAT and levy remittances, eight PAYE and SSNIT payments and two withholding tax remittances. Payments to that counterparty which are not tax settlements are excluded by the keyword test.
B46: 5. This workbook is a simulation built on fictitious data. It is a control and reporting tool, not tax advice. Confirm all rates and treatments with the Ghana Revenue Authority before filing.

Sheet Error_Key
B1: NKABOM HAULAGE LTD — CORE TAX ENGINE
B2: Error Key • Answer sheet for the 12 errors seeded into the Ledger • Restricted
B3: CONTROL TESTING AID — These errors were deliberately planted so the Error_Flags controls can be proven to work. The Ledger itself carries no marking. Withhold this sheet from anyone testing the controls.
B5: Row ID | C5: Error type | D5: Correct value | E5: Recorded category | F5: Date | G5: Amount | H5: Description | I5: Invoice on Ledger | J5: How the error was introduced
B6: 65 | C6: Wrong tax category | D6: IN_EXEMPT | E6: IN_STD | F6: 46075 | G6: 52400 | H6: Diesel (AGO) purchased for own fleet use, 14,500 litres | I6: SIN-2026-0023 | J6: Recorded IN_STD; the transaction is an exempt supply
B7: 70 | C7: Duplicate invoice number | D7: NHL-2026-0034 | E7: OUT_STD | F7: 46080 | G7: 60662 | H7: Bulk haulage of AGO, Takoradi-Tamale, 2 trips | I7: NHL-2026-0090 | J7: Re-uses NHL-2026-0090, already issued on Row ID 242
B8: 93 | C8: Missing invoice number | D8: NHL-2026-0044 | E8: OUT_STD | F8: 46095 | G8: 92487 | H8: Bulk haulage of AGO, Tema-Cape Coast, 6 trips | I8: (blank) | J8: Invoice number left blank on capture
B9: 99 | C9: Duplicate invoice number | D9: SIN-2026-0034 | E9: IN_STD | F9: 46098 | G9: 4906 | H9: Workshop consumables and lubricants | I9: SIN-2026-0081 | J9: Re-uses SIN-2026-0081, already issued on Row ID 197
B10: 101 | C10: Wrong tax amount | D10: 0 | E10: IN_EXEMPT | F10: 46100 | G10: 521 | H10: Transfer and settlement charges | I10: BNK-2026-0010 | J10: Tax charged on an exempt supply; expected nil
B11: 103 | C11: Wrong tax category | D11: IN_EXEMPT | E11: IN_STD | F11: 46101 | G11: 21750 | H11: Motor fleet insurance premium | I11: SIN-2026-0036 | J11: Recorded IN_STD; the transaction is an exempt supply
B12: 114 | C12: Missing invoice number | D12: SIN-2026-0040 | E12: IN_STD | F12: 46110 | G12: 8752 | H12: Fleet tracking software subscription | I12: (blank) | J12: Invoice number left blank on capture
B13: 142 | C13: Wrong tax amount | D13: 485.6 | E13: IN_STD | F13: 46135 | G13: 2428 | H13: Mobile and data services | I13: SIN-2026-0055 | J13: Digits transposed when the invoice was keyed (845.60 entered)
B14: 216 | C14: Duplicate invoice number | D14: NHL-2026-0081 | E14: WHT_SVC | F14: 46194 | G14: 101340 | H14: Contract haulage of ATK, Takoradi-Tamale; income tax withheld | I14: NHL-2026-0072 | J14: Re-uses NHL-2026-0072, already issued on Row ID 179
B15: 225 | C15: Wrong tax category | D15: NO_VAT | E15: IN_STD | F15: 46202 | G15: 68300 | H15: Staff salaries and wages - supplementary run | I15: SIN-2026-0093 | J15: Recorded IN_STD; the payment is outside the scope of VAT
B16: 240 | C16: Wrong tax amount | D16: 14390.4 | E16: OUT_STD | F16: 46213 | G16: 71952 | H16: Bulk haulage of LPG, Takoradi-Wa, 8 trips | I16: NHL-2026-0089 | J16: VAT charged at 15% only; NHIL and GETFund omitted (10,792.80 entered)
B17: 252 | C17: Missing invoice number | D17: BNK-2026-0019 | E17: IN_EXEMPT | F17: 46228 | G17: 498 | H17: Cheque book and facility fees | I17: (blank) | J17: Invoice number left blank on capture
